Workbook

Sheet Datos
A1: Marca temporal | B1: ¿En qué país resides? | C1: Tu edad está dentro del rango: | D1: ¿Tu género es? | E1: Indica tu nivel de estudios: | F1: Actualmente trabajas: | G1: En el caso de trabajar para una empresa, indica en qué país está su sede principal: | H1: Indica los años de experiencia trabajando en empresas de desarrollo de software: | I1: Indica los años que has trabajado de forma presencial | J1: Por favor indica el puesto que ocupabas cuando trabajabas presencialmente en la empresa: | K1: Por favor indica el puesto que ocupas actualmente en la empresa: | L1: Nombre de la compañía (opcional): | M1: Tamaño de la compañía | N1: Tipo de empresa: | O1: Tu empresa es: | P1: ¿En tu trabajo te comunicas con personas de distintos países? | Q1: NIVEL HOMEOFFICE | R1: ¿Cuántos días a la semana trabajas desde casa actualmente? | S1: ¿Cuántos días a la semana vas a la oficina actualmente? | T1: ¿Si tu contrato no te obliga a ir a la oficina ningún día a la semana indica en qué ocasiones se te ha solicitado ir a la oficina? | U1: En el caso de que tu empresa te obligue a ir a la oficina algún día a la semana, indica en qué ocasiones has tenido que asistir: | V1: En el caso de que tu empresa te recomiende a ir a la oficina algún día a la semana, indica en qué ocasiones se te ha solicitado: | W1: Si te ofrece tu empresa alguna clase de recompensa por ir a la oficina (parking gratuito, tickets para comidas, mejora en las instalaciones.), indica cuáles son: | X1: ¿Qué modalidad de trabajo prefieres? | Y1: La modalidad que actualmente tienes fue: | Z1: Trabajo la misma cantidad de horas que cuando trabajaba todos los días en la oficina | AA1: El intercambio de conocimiento con mis compañeros de proyecto es ahora: | AB1: La comunicación en general con mis compañeros de proyecto es ahora | AC1: La comunicación con mis jefes es ahora | AD1: Tus horarios de trabajo ahora son: | AE1: Mis reuniones ahora son: | AF1: El cansancio después de una reunión online es ahora: | AG1: Siento que mi rendimiento ahora es: | AH1: Siento que la productividad de mi equipo es: | AI1: Siento que la capacidad de mi equipo para cumplir hitos es: | AJ1: Siento que mi concentración cuando estoy trabajando es: | AK1: Siento que la velocidad de mi conexión a Internet es | AL1: Siento que la eficiencia de la conexión a Internet me influye: | AM1: Las herramientas de comunicación (Teams, Zoom, Slack,...) utilizadas por mi empresa, desde casa: | AN1: Siento que la facilidad para compartir conocimiento ahora es: | AO1: Siento que el impacto de la rotación de personal en la empresa ahora es: | AP1: Siento que la falta de compromiso por parte de los empleados, afecta a la productividad: | AQ1: Siento que el hecho de trabajar con personas de distintas culturas afecta a la productividad: | AR1: Siento que el hecho de trabajar con personas que tienen otros horarios afecta a la productividad | AS1: Siento que el hecho de trabajar con personas que se encuentran geográficamente distribuidas afecta a la productividad: | AT1: Siento que la falta de confianza entre los miembros del equipo afecta la productividad | AU1: Siento que la falta de colaboración entre los miembros del equipo afecta la productividad: | AV1: Siento que la falta de relaciones personales entre los miembros del equipo afecta la productividad: | AW1: Siento que la falta de cohesión y de espíritu de grupo afecta la productividad | AX1: Siento que los problemas de liderazgo afectan la productividad | AY1: Siento que el nivel de la definición de los requisitos de software y su calidad son ahora: | AZ1: Siento que el control de los cambios de los requisitos es ahora: | BA1: Siento que la cantidad de personal cualificado en la empresa es ahora: | BB1: Siento que mi nivel de estrés es: | BC1: Siento que mi nivel de confianza para enfrentarme a los retos del trabajo es: | BD1: Siento que mis reacciones de enojo o molestia ahora son: | BE1: Siento que mi nivel de frustración con relación al trabajo es: | BF1: Siento que el nivel de presión por terminar las tareas ahora es: | BG1: Siento que la flexibilidad de mi trabajo ahora es: | BH1: Siento que los problemas tecnológicos ahora son: | BI1: Siento que la facilidad para trabajar en equipos distribuidos es: | BJ1: Siento que los problemas que aparecen por las diferencias culturales ahora son: | BK1: Siento que la aplicación de metodología ágiles ahora es: | BL1: Siento que los problemas de comunicación ahora son: | BM1: Siento que los problemas por usar distintos idiomas ahora son: | BN1: Siento que el hecho de trabajar con personas que tienen otros horarios afecta a mi estrés: | BO1: Siento que la generación de confianza entre los miembros del equipo ahora es: | BP1: Siento que las interrupciones externas ahora son: | BQ1: Siento que ahora mi manejo del tiempo en general es: | BR1: Siento que la falta de compañerismo ahora es: | BS1: Siento que los problemas de coordinación afectan a mi estrés: | BT1: Siento que los problemas vinculados con la gestión del proyecto ahora son: | BU1: Siento que la asignación de tareas entre los miembros del equipo ahora es: | BV1: Siento que mi nivel de motivación en el trabajo es: | BW1: Mi concentración ahora cuando estoy trabajando es: | BX1: Mi comodidad ahora cuando estoy trabajando es: | BY1: Mi seguridad/ confianza a la hora de preguntar a un compañero ahora es: | BZ1: Mi confianza para hacer preguntas a un superior ahora es: | CA1: Mi habilidad para resolver problemas ahora es: | CB1: En términos de disfrute en el trabajo siento que ahora es: | CC1: Siento que el nivel de interés hacia mi trabajo ahora es: | CD1: Siento que la falta de conocimiento sobre el rol de cada miembro del equipo ahora es: | CE1: Siento que mi empresa me aprecia: | CF1: Siento que las acciones de motivación de personal de mi empresa son: | CG1: Siento que la calidad del desarrollo de software es ahora: | CH1: Siento que el equilibrio vida personal - trabajo es ahora: | CI1: Siento que ahora la retroalimentación que recibo por parte de mis compañeros y superiores es: | CJ1: Siento que mi nivel de aburrimiento en el trabajo es ahora: | CK1: Siento que mi nivel de atención a cada individuo es ahora: | CL1: Siento que mi miedo a perder el trabajo es ahora: | CM1: Siento que el ambiente de trabajo ahora es: | CN1: Siento que mi nivel de influencia en mi equipo de trabajo es ahora: | CO1: Siento que la facilidad para desarrollar relaciones personales entre los compañeros de trabajo es ahora | CP1: Siento que la participación de los miembros en los proyectos de mi equipo es ahora: | CQ1: Siento que el nivel de autonomía en el trabajo es ahora | CR1: Siento que el nivel de relaciones conflictivas entre compañeros es ahora: | CS1: Siento que los problemas relacionados con el liderazgo compartido son ahora: | CT1: El sentimiento de pertenencia a mi empresa es ahora | CU1: Siento que mi creatividad es: | CV1: Correo electrónico para recibir resultados (opcional) | CW1: Tam_Empresa | CX1: Lead | CY1: =_xlfn.TEXTJOIN(",",FALSE,A1:CX1) -> Marca temporal,¿En qué país resides?,Tu edad está dentro del rango:,¿Tu género es?,Indica tu nivel de estudios:,Actualmente trabajas:,En el caso de trabajar para una empresa, indica en qué país está su sede principal:,Indica los años de experiencia trabajando en empresas de desarrollo de software:,Indica los años que has trabajado de forma presencial,Por favor indica el puesto que ocupabas cuando trabajabas presencialmente en la empresa:,Por favor indica el puesto que ocupas actualmente en la empresa:,Nombre de la compañía (opcional):,Tamaño de la compañía,Tipo de empresa:,Tu empresa es:,¿En tu trabajo te comunicas con personas de distintos países?,NIVEL HOMEOFFICE,¿Cuántos días a la semana trabajas desde casa actualmente?,¿Cuántos días a la semana vas a la oficina actualmente?,¿Si tu contrato no te obliga a ir a la oficina ningún día a la semana indica en qué ocasiones se te ha solicitado ir a la oficina?,En el caso de que tu empresa te obligue a ir a la oficina algún día a la semana, indica en qué ocasiones has tenido que asistir:,En el caso de que tu empresa te recomiende a ir a la oficina algún día a la semana, indica en qué ocasiones se te ha solicitado:,Si te ofrece tu empresa alguna clase de recompensa por ir a la oficina (parking gratuito, tickets para comidas, mejora en las instalaciones.), indica cuáles son:,¿Qué modalidad de trabajo prefieres?,La modalidad que actualmente tienes fue:,Trabajo la misma cantidad de horas que cuando trabajaba todos los días en la oficina,El intercambio de conocimiento con mis compañeros de proyecto es ahora:,La comunicación en general con mis compañeros de proyecto es ahora,La comunicación con mis jefes es ahora,Tus horarios de trabajo ahora son:,Mis reuniones ahora son:,El cansancio después de una reunión online es ahora:,Siento que mi rendimiento ahora es:,Siento que la productividad de mi equipo es:,Siento que la capacidad de mi equipo para cumplir hitos es:,Siento que mi concentración cuando estoy trabajando es:,Siento que la velocidad de mi conexión a Internet es,Siento que la eficiencia de la conexión a Internet me influye:,Las herramientas de comunicación (Teams, Zoom, Slack,...) utilizadas por mi empresa, desde casa:,Siento que la facilidad para compartir conocimiento ahora es: ,Siento que el impacto de la rotación de personal en la empresa ahora es: ,Siento que la falta de compromiso por parte de los empleados, afecta a la productividad:,Siento que el hecho de trabajar con personas de distintas culturas afecta a la productividad:,Siento que el hecho de trabajar con personas que tienen otros horarios afecta a la productividad,Siento que el hecho de trabajar con personas que se encuentran geográficamente distribuidas afecta a la productividad:,Siento que la falta de confianza entre los miembros del equipo afecta la productividad,Siento que la falta de colaboración entre los miembros del equipo afecta la productividad:,Siento que la falta de relaciones personales entre los miembros del equipo afecta la productividad:,Siento que la falta de cohesión y de espíritu de grupo afecta la productividad,Siento que los problemas de liderazgo afectan la productividad,Siento que el nivel de la definición de los requisitos de software y su calidad son ahora:,Siento que el control de los cambios de los requisitos es ahora:,Siento que la cantidad de personal cualificado en la empresa es ahora:,Siento que mi nivel de estrés es:,Siento que mi nivel de confianza para enfrentarme a los retos del trabajo es: ,Siento que mis reacciones de enojo o molestia ahora son:,Siento que mi nivel de frustración con relación al trabajo es: ,Siento que el nivel de presión por terminar las tareas ahora es:,Siento que la flexibilidad de mi trabajo ahora es:,Siento que los problemas tecnológicos ahora son:,Siento que la facilidad para trabajar en equipos distribuidos es:,Siento que los problemas que aparecen por las diferencias culturales ahora son:,Siento que la aplicación de metodología ágiles ahora es:,Siento que los problemas de comunicación ahora son:,Siento que los problemas por usar distintos idiomas ahora son:,Siento que el hecho de trabajar con personas que tienen otros horarios afecta a mi estrés:,Siento que la generación de confianza entre los miembros del equipo ahora es:,Siento que las interrupciones externas ahora son:,Siento que ahora mi manejo del tiempo en general es:,Siento que la falta de compañerismo ahora es:,Siento que los problemas de coordinación afectan a mi estrés:,Siento que los problemas vinculados con la gestión del proyecto ahora son:,Siento que la asignación de tareas entre los miembros del equipo ahora es:,Siento que mi nivel de motivación en el trabajo es:,Mi concentración ahora cuando estoy trabajando es:,Mi comodidad ahora cuando estoy trabajando es:,Mi seguridad/ confianza a la hora de preguntar a un compañero ahora es:,Mi confianza para hacer preguntas a un superior ahora es:,Mi habilidad para resolver problemas ahora es:,En términos de disfrute en el trabajo siento que ahora es:,Siento que el nivel de interés hacia mi trabajo ahora es: ,Siento que la falta de conocimiento sobre el rol de cada miembro del equipo ahora es:,Siento que mi empresa me aprecia:,Siento que las acciones de motivación de personal de mi empresa son:,Siento que la calidad del desarrollo de software es ahora:,Siento que el equilibrio vida personal - trabajo es ahora:,Siento que ahora la retroalimentación que recibo por parte de mis compañeros y superiores es:,Siento que mi nivel de aburrimiento en el trabajo es ahora:,Siento que mi nivel de atención a cada individuo es ahora:,Siento que mi miedo a perder el trabajo es ahora:,Siento que el ambiente de trabajo ahora es:,Siento que mi nivel de influencia en mi equipo de trabajo es ahora:,Siento que la facilidad para desarrollar relaciones personales entre los compañeros de trabajo es ahora,Siento que la participación de los miembros en los proyectos de mi equipo es ahora:,Siento que el nivel de autonomía en el trabajo es ahora,Siento que el nivel de relaciones conflictivas entre compañeros es ahora:,Siento que los problemas relacionados con el liderazgo compartido son ahora:,El sentimiento de pertenencia a mi empresa es ahora,Siento que mi creatividad es:,Correo electrónico para recibir resultados (opcional),Tam_Empresa,Lead
A2: 45594.111 | B2: Argentina | C2: <35 años | D2: Masculino | E2: Universitarios completo | F2: Como empleado de una empresa | G2: Argentina | H2: 5-10 años | I2: <5 años | J2: Desarrollador de Software | K2: Líder Técnico | M2: >500 empleados. | N2: Empresa que desarrolla software a medida partiendo desde cero | O2: Multinacional | P2: Muy Frecuentemente | Q2: Alto | R2: >5 días | S2: Ninguno | T2: Se me solicita ir a una sede una vez cada 3 meses aproximadamente | W2: Parking gratuito, descuentos en accesorios electrónicos de uso personal si se adquiere en la sede | X2: Remota ( todos los días en casa) | Y2: Consensuada por las dos partes | Z2: En desacuerdo | AA2: Igual que cuando iba todos los días a la oficina | AB2: Igual que cuando iba todos los días a la oficina | AC2: Mayor que cuando iba todos los días a la oficina | AD2: Diferentes que cuando iba todos los días a la oficina, ahora necesito menos horas para hacer lo mismo | AE2: Todas por videoconferencia | AF2: Igual que cuando eran en la oficina | AG2: Mayor que cuando iba todos los días a la oficina | AH2: Mayor que cuando iba todos los días a la oficina | AI2: Mayor que cuando iba todos los días a la oficina | AJ2: Mucho Mayor que cuando iba todos los días a la oficina | AK2: Mucho Mejor que cuando iba todos los días a la oficina | AL2: Mejora mucho mi desempeño en el trabajo | AM2: Mejoran mi productividad | AN2: Menor que cuando iba todos los días a la oficina | AO2: Mucho mayor que cuando iba todos los días a la oficina | AP2: Igual que cuando iba todos los días a la oficina | AQ2: Igual que cuando iba todos los días a la oficina | AR2: Mucho menos que cuando iba todos los días a la oficina | AS2: Mucho menos que cuando iba todos los días a la oficina | AT2: Más que cuando iba todos los días a la oficina | AU2: Igual que cuando iba todos los días a la oficina | AV2: Mas que cuando iba todos los días a la oficina | AW2: Igual que cuando iba todos los días a la oficina | AX2: Mas que cuando iba todos los días a la oficina | AY2: Mayores que cuando iba todos los días a la oficina | AZ2: Mucho Mayor que cuando iba todos los días a la oficina | BA2: Mucho Mayor que cuando iba todos los días a la oficina | BB2: Igual que cuando iba todos los días a la oficina | BC2: Mayor que cuando iba todos los días a la oficina | BD2: Menor que cuando iba todos los días a la oficina | BE2: Menor que cuando iba todos los días a la oficina | BF2: Mayor que cuando iba todos los días a la oficina | BG2: Mucho mayor que cuando iba todos los días a la oficina | BH2: Menores que cuando iba todos los días a la oficina | BI2: Mucho mayor que cuando iba todos los días a la oficina | BJ2: Iguales que cuando iba todos los días a la oficina | BK2: Mucho mayor que cuando iba todos los días a la oficina | BL2: Menores que cuando iba todos los días a la oficina | BM2: Menores que cuando iba todos los días a la oficina | BN2: Igual que cuando iba todos los días a la oficina | BO2: Menor que cuando iba todos los días a la oficina | BP2: Mayores que cuando iba todos los días a la oficina | BQ2: Mucho mayor que cuando iba todos los días a la oficina | BR2: Menor que cuando iba todos los días a la oficina | BS2: Igual que cuando iba todos los días a la oficina | BT2: Iguales que cuando iba todos los días a la oficina | BU2: Mejor que cuando iba todos los días a la oficina | BV2: Mucho Mayor que cuando iba todos los días a la oficina | BW2: Mayor que cuando iba todos los días a la oficina | BX2: Mayor que cuando iba todos los días a la oficina | BY2: Menor que cuando iba todos los días a la oficina | BZ2: Mayor que cuando iba todos los días a la oficina | CA2: Igual que cuando iba todos los días a la oficina | CB2: Mucho Mayor que cuando iba todos los días a la oficina | CC2: Igual que cuando iba todos los días a la oficina | CD2: Mayor que cuando iba todos los días a la oficina | CE2: Menos que cuando iba todos los días a la oficina | CF2: Iguales que cuando iba todos los días a la oficina | CG2: Mayor que cuando iba todos los días a la oficina | CH2: Mucho Mayor que cuando iba todos los días a la oficina | CI2: Mayor que cuando iba todos los días a la oficina | CJ2: Menor que cuando iba todos los días a la oficina | CK2: Mayor que cuando iba todos los días a la oficina | CL2: Mayor que cuando iba todos los días a la oficina | CM2: Igual que cuando iba todos los días a la oficina | CN2: Menor que cuando iba todos los días a la oficina | CO2: Menor que cuando iba todos los días a la oficina | CP2: Mayor que cuando iba todos los días a la oficina | CQ2: Mucho Mayor que cuando iba todos los días a la oficina | CR2: Mucho menor que cuando iba todos los días a la oficina | CS2: Menores que cuando iba todos los días a la oficina | CT2: Igual que cuando iba todos los días a la oficina | CU2: Igual que cuando iba todos los días a la oficina | CV2: juan.delafuente@fi.uncoma.edu.ar | CW2: 301+ empleados | CX2: =VLOOKUP(K2,Sheet2!$A$2:$B$58,2,0) -> 0 | CY2: =_xlfn.TEXTJOIN(",",FALSE,A2:CX2) -> 45594,1107893982,Argentina,<35 años,Masculino,Universitarios completo,Como empleado de una empresa,Argentina,5-10 años,<5 años,Desarrollador de Software,Líder Técnico ,,>500 empleados.,Empresa que desarrolla software a medida partiendo desde cero,Multinacional,Muy Frecuentemente,Alto,>5 días,Ninguno,Se me solicita ir a una sede una vez cada 3 meses aproximadamente,,,Parking gratuito, descuentos en accesorios electrónicos de uso personal si se adquiere en la sede,Remota ( todos los días en casa),Consensuada por las dos partes,En desacuerdo,Igual que cuando iba todos los días a la oficina,Igual que cuando iba todos los días a la oficina,Mayor que cuando iba todos los días a la oficina,Diferentes que cuando iba todos los días a la oficina, ahora necesito menos horas para hacer lo mismo,Todas por videoconferencia,Igual que cuando eran en la oficina,Mayor que cuando iba todos los días a la oficina,Mayor que cuando iba todos los días a la oficina,Mayor que cuando iba todos los días a la oficina,Mucho Mayor que cuando iba todos los días a la oficina,Mucho Mejor que cuando iba todos los días a la oficina,Mejora mucho mi desempeño en el trabajo,Mejoran mi productividad,Menor que cuando iba todos los días a la oficina,Mucho mayor que cuando iba todos los días a la oficina,Igual que cuando iba todos los días a la oficina,Igual que cuando iba todos los días a la oficina,Mucho menos que cuando iba todos los días a la oficina,Mucho menos que cuando iba todos los días a la oficina,Más que cuando iba todos los días a la oficina,Igual que cuando iba todos los días a la oficina,Mas que cuando iba todos los días a la oficina,Igual que cuando iba todos los días a la oficina,Mas que cuando iba todos los días a la oficina,Mayores que cuando iba todos los días a la oficina,Mucho Mayor que cuando iba todos los días a la oficina,Mucho Mayor que cuando iba todos los días a la oficina,Igual que cuando iba todos los días a la oficina,Mayor que cuando iba todos los días a la oficina,Menor que cuando iba todos los días a la oficina,Menor que cuando iba todos los días a la oficina,Mayor que cuando iba todos los días a la oficina,Mucho mayor que cuando iba todos los días a la oficina,Menores que cuando iba todos los días a la oficina,Mucho mayor que cuando iba todos los días a la oficina,Iguales que cuando iba todos los días a la oficina,Mucho mayor que cuando iba todos los días a la oficina,Menores que cuando iba todos los días a la oficina,Menores que cuando iba todos los días a la oficina,Igual que cuando iba todos los días a la oficina,Menor que cuando iba todos los días a la oficina,Mayores que cuando iba todos los días a la oficina,Mucho mayor que cuando iba todos los días a la oficina,Menor que cuando iba todos los días a la oficina,Igual que cuando iba todos los días a la oficina,Iguales que cuando iba todos los días a la oficina,Mejor que cuando iba todos los días a la oficina,Mucho Mayor que cuando iba todos los días a la oficina,Mayor que cuando iba todos los días a la oficina,Mayor que cuando iba todos los días a la oficina,Menor que cuando iba todos los días a la oficina,Mayor que cuando iba todos los días a la oficina,Igual que cuando iba todos los días a la oficina,Mucho Mayor que cuando iba todos los días a la oficina,Igual que cuando iba todos los días a la oficina,Mayor que cuando iba todos los días a la oficina,Menos que cuando iba todos los días a la oficina,Iguales que cuando iba todos los días a la oficina,Mayor que cuando iba todos los días a la oficina,Mucho Mayor que cuando iba todos los días a la oficina,Mayor que cuando iba todos los días a la oficina,Menor que cuando iba todos los días a la oficina,Mayor que cuando iba todos los días a la oficina,Mayor que cuando iba todos los días a la oficina,Igual que cuando iba todos los días a la oficina,Menor que cuando iba todos los días a la oficina,Menor que cuando iba todos los días a la oficina,Mayor que cuando iba todos los días a la oficina,Mucho Mayor que cuando iba todos los días a la oficina,Mucho menor que cuando iba todos los días a la oficina,Menores que cuando iba todos los días a la oficina,Igual que cuando iba todos los días a la oficina,Igual que cuando iba todos los días a la oficina,juan.delafuente@fi.uncoma.edu.ar,301+ empleados,0
A3: 45572.098 | B3: Argentina | C3: <35 años | D3: Femenino | E3: universitario | F3: De ambas formas | G3: Argentina | H3: 21-30 años | I3: 5-10 años | J3: Referente IT | K3: COO | M3: <50 empleados | N3: Empresa que desarrolla software a medida partiendo desde cero | O3: Multinacional | P3: Casi Nunca | Q3: Alto | R3: >5 días | S3: Ninguno | T3: Encuentros del equipo, reuniones gerenciales o con cliente | V3: Reuniones de equipo, lo deja a discreciónd el equipo | X3: Remota ( todos los días en casa) | Y3: Decidida por ti | Z3: En desacuerdo | AA3: Mayor que cuando iba todos los días a la oficina | AB3: Mayor que cuando iba todos los días a la oficina | AC3: Mayor que cuando iba todos los días a la oficina | AD3: Diferentes que cuando iba todos los días a la oficina, ahora necesito menos horas para hacer lo mismo | AE3: Casi todas por videoconferencia | AF3: Menor que cuando eran en la oficina | AG3: Mayor que cuando iba todos los días a la oficina | AH3: Mucho Mayor que cuando iba todos los días a la oficina | AI3: Mucho Mayor que cuando iba todos los días a la oficina | AJ3: Mayor que cuando iba todos los días a la oficina | AK3: Mucho Mejor que cuando iba todos los días a la oficina | AL3: Mejora mucho mi desempeño en el trabajo | AM3: No afectan a mi productividad | AN3: Igual que cuando iba todos los días a la oficina | AO3: Igual que cuando iba todos los días a la oficina | AP3: Igual que cuando iba todos los días a la oficina | AQ3: No trabajo con personas de distintas culturas | AR3: Mucho menos que cuando iba todos los días a la oficina | AS3: Mucho menos que cuando iba todos los días a la oficina | AT3: Igual que cuando iba todos los días a la oficina | AU3: Igual que cuando iba todos los días a la oficina | AV3: Igual que cuando iba todos los días a la oficina | AW3: Igual que cuando iba todos los días a la oficina | AX3: Igual que cuando iba todos los días a la oficina | AY3: Menores que cuando iba todos los días a la oficina | AZ3: Igual que cuando iba todos los días a la oficina | BA3: Igual que cuando iba todos los días a la oficina | BB3: Mucho menor que cuando iba todos los días a la oficina | BC3: Igual que cuando iba todos los días a la oficina | BD3: Igual que cuando iba todos los días a la oficina | BE3: Igual que cuando iba todos los días a la oficina | BF3: Igual que cuando iba todos los días a la oficina | BG3: Mucho mayor que cuando iba todos los días a la oficina | BH3: Mucho menores que cuando iba todos los días a la oficina | BI3: Mucho menor que cuando iba todos los días a la oficina | BJ3: No hay diferencias culturales en mi equipo | BK3: Mayor que cuando iba todos los días a la oficina | BL3: Iguales que cuando iba todos los días a la oficina | BM3: No tengo que utilizar diferentes idiomas en mi trabajo | BN3: Menos que cuando iba todos los días a la oficina | BO3: Igual que cuando iba todos los días a la oficina | BP3: Mucho menores que cuando iba todos los días a la oficina | BQ3: Mucho mayor que cuando iba todos los días a la oficina | BR3: Menor que cuando iba todos los días a la oficina | BS3: Menos que cuando iba todos los días a la oficina | BT3: Menores que cuando iba todos los días a la oficina | BU3: Igual que cuando iba todos los días a la oficina | BV3: Mayor que cuando iba todos los días a la oficina | BW3: Mayor que cuando iba todos los días a la oficina | BX3: Mayor que cuando iba todos los días a la oficina | BY3: Igual que cuando iba todos los días a la oficina | BZ3: Igual que cuando iba todos los días a la oficina | CA3: Igual que cuando iba todos los días a la oficina | CB3: Mayor que cuando iba todos los días a la oficina | CC3: Igual que cuando iba todos los días a la oficina | CD3: Igual que cuando iba todos los días a la oficina | CE3: Menos que cuando iba todos los días a la oficina | CF3: Iguales que cuando iba todos los días a la oficina | CG3: Mayor que cuando iba todos los días a la oficina | CH3: Mucho Mayor que cuando iba todos los días a la oficina | CI3: Mayor que cuando iba todos los días a la oficina | CJ3: Menor que cuando iba todos los días a la oficina | CK3: Menor que cuando iba todos los días a la oficina | CL3: Menor que cuando iba todos los días a la oficina | CM3: Mejor que cuando iba todos los días a la oficina | CN3: Mayor que cuando iba todos los días a la oficina | CO3: Igual que cuando iba todos los días a la oficina | CP3: Mayor que cuando iba todos los días a la oficina | CQ3: Mayor que cuando iba todos los días a la oficina | CR3: Menor que cuando iba todos los días a la oficina | CS3: Menores que cuando iba todos los días a la oficina | CT3: Menor que cuando iba todos los días a la oficina | CU3: Mayor que cuando iba todos los días a la oficina | CV3: baeza.natalia@gmail.com | CW3: <301 empleados | CX3: =VLOOKUP(K3,Sheet2!$A$2:$B$58,2,0) -> 1 | CY3: =_xlfn.TEXTJOIN(",",FALSE,A3:CX3) -> 45572,0978002431,Argentina,<35 años,Femenino,universitario,De ambas formas,Argentina,21-30 años,5-10 años,Referente IT,COO,,<50 empleados,Empresa que desarrolla software a medida partiendo desde cero,Multinacional,Casi Nunca,Alto,>5 días,Ninguno,Encuentros del equipo, reuniones gerenciales o con cliente,,Reuniones de equipo, lo deja a discreciónd el equipo,,Remota ( todos los días en casa),Decidida por ti,En desacuerdo,Mayor que cuando iba todos los días a la oficina,Mayor que cuando iba todos los días a la oficina,Mayor que cuando iba todos los días a la oficina,Diferentes que cuando iba todos los días a la oficina, ahora necesito menos horas para hacer lo mismo,Casi todas por videoconferencia,Menor que cuando eran en la oficina,Mayor que cuando iba todos los días a la oficina,Mucho Mayor que cuando iba todos los días a la oficina,Mucho Mayor que cuando iba todos los días a la oficina,Mayor que cuando iba todos los días a la oficina,Mucho Mejor que cuando iba todos los días a la oficina,Mejora mucho mi desempeño en el trabajo,No afectan a mi productividad,Igual que cuando iba todos los días a la oficina,Igual que cuando iba todos los días a la oficina,Igual que cuando iba todos los días a la oficina,No trabajo con personas de distintas culturas,Mucho menos que cuando iba todos los días a la oficina,Mucho menos que cuando iba todos los días a la oficina,Igual que cuando iba todos los días a la oficina,Igual que cuando iba todos los días a la oficina,Igual que cuando iba todos los días a la oficina,Igual que cuando iba todos los días a la oficina,Igual que cuando iba todos los días a la oficina,Menores que cuando iba todos los días a la oficina,Igual que cuando iba todos los días a la oficina,Igual que cuando iba todos los días a la oficina,Mucho menor que cuando iba todos los días a la oficina,Igual que cuando iba todos los días a la oficina,Igual que cuando iba todos los días a la oficina,Igual que cuando iba todos los días a la oficina,Igual que cuando iba todos los días a la oficina,Mucho mayor que cuando iba todos los días a la oficina,Mucho menores que cuando iba todos los días a la oficina,Mucho menor que cuando iba todos los días a la oficina,No hay diferencias culturales en mi equipo,Mayor que cuando iba todos los días a la oficina,Iguales que cuando iba todos los días a la oficina,No tengo que utilizar diferentes idiomas en mi trabajo,Menos que cuando iba todos los días a la oficina,Igual que cuando iba todos los días a la oficina,Mucho menores que cuando iba todos los días a la oficina,Mucho mayor que cuando iba todos los días a la oficina,Menor que cuando iba todos los días a la oficina,Menos que cuando iba todos los días a la oficina,Menores que cuando iba todos los días a la oficina,Igual que cuando iba todos los días a la oficina,Mayor que cuando iba todos los días a la oficina,Mayor que cuando iba todos los días a la oficina,Mayor que cuando iba todos los días a la oficina,Igual que cuando iba todos los días a la oficina,Igual que cuando iba todos los días a la oficina,Igual que cuando iba todos los días a la oficina,Mayor que cuando iba todos los días a la oficina,Igual que cuando iba todos los días a la oficina,Igual que cuando iba todos los días a la oficina,Menos que cuando iba todos los días a la oficina,Iguales que cuando iba todos los días a la oficina,Mayor que cuando iba todos los días a la oficina,Mucho Mayor que cuando iba todos los días a la oficina,Mayor que cuando iba todos los días a la oficina,Menor que cuando iba todos los días a la oficina,Menor que cuando iba todos los días a la oficina,Menor que cuando iba todos los días a la oficina,Mejor que cuando iba todos los días a la oficina,Mayor que cuando iba todos los días a la oficina,Igual que cuando iba todos los días a la oficina,Mayor que cuando iba todos los días a la oficina,Mayor que cuando iba todos los días a la oficina,Menor que cuando iba todos los días a la oficina,Menores que cuando iba todos los días a la oficina,Menor que cuando iba todos los días a la oficina,Mayor que cuando iba todos los días a la oficina,baeza.natalia@gmail.com,<301 empleados,1
A4: 45573.063 | B4: Colombia | C4: <35 años | D4: Masculino | E4: Profesional | F4: Como empleado de una empresa | G4: Bogotá | H4: 5-10 años | I4: 5-10 años | J4: Desarollador junior | K4: Líder técnico de desarrollo | L4: Lulo bank | M4: 151-300 empleados | N4: Empresa que desarrolla software a medida partiendo desde cero | O4: Local | P4: Casi Nunca | Q4: Alto | R4: >5 días | S4: Ninguno | T4: A integraciones de trabajo | X4: Remota ( todos los días en casa) | Y4: Impuesta por la empresa | Z4: Totalmente en desacuerdo | AA4: Igual que cuando iba todos los días a la oficina | AB4: Igual que cuando iba todos los días a la oficina | AC4: Igual que cuando iba todos los días a la oficina | AD4: Iguales que cuando iba todos los días a la oficina | AE4: Todas por videoconferencia | AF4: Igual que cuando eran en la oficina | AG4: Mayor que cuando iba todos los días a la oficina | AH4: Mucho Mayor que cuando iba todos los días a la oficina | AI4: Mayor que cuando iba todos los días a la oficina | AJ4: Mayor que cuando iba todos los días a la oficina | AK4: Igual que cuando iba todos los días a la oficina | AL4: Mejora mi desempeño en el trabajo | AM4: Mejoran mi productividad | AN4: Igual que cuando iba todos los días a la oficina | AO4: Igual que cuando iba todos los días a la oficina | AP4: Igual que cuando iba todos los días a la oficina | AQ4: Igual que cuando iba todos los días a la oficina | AR4: Igual que cuando iba todos los días a la oficina | AS4: Igual que cuando iba todos los días a la oficina | AT4: Igual que cuando iba todos los días a la oficina | AU4: Igual que cuando iba todos los días a la oficina | AV4: Igual que cuando iba todos los días a la oficina | AW4: Igual que cuando iba todos los días a la oficina | AX4: Igual que cuando iba todos los días a la oficina | AY4: Iguales que cuando iba todos los días a la oficina | AZ4: Igual que cuando iba todos los días a la oficina | BA4: Igual que cuando iba todos los días a la oficina | BB4: Igual que cuando iba todos los días a la oficina | BC4: Igual que cuando iba todos los días a la oficina | BD4: Igual que cuando iba todos los días a la oficina | BE4: Igual que cuando iba todos los días a la oficina | BF4: Igual que cuando iba todos los días a la oficina | BG4: Igual que cuando iba todos los días a la oficina | BH4: Iguales que cuando iba todos los días a la oficina | BI4: Igual que cuando iba todos los días a la oficina | BJ4: Iguales que cuando iba todos los días a la oficina | BK4: Mayor que cuando iba todos los días a la oficina | BL4: Iguales que cuando iba todos los días a la oficina | BM4: Iguales que cuando iba todos los días a la oficina | BN4: Igual que cuando iba todos los días a la oficina | BO4: Igual que cuando iba todos los días a la oficina | BP4: Iguales que cuando iba todos los días a la oficina | BQ4: Igual que cuando iba todos los días a la oficina | BR4: Igual que cuando iba todos los días a la oficina | BS4: Igual que cuando iba todos los días a la oficina | BT4: Iguales que cuando iba todos los días a la oficina | BU4: Igual que cuando iba todos los días a la oficina | BV4: Igual que cuando iba todos los días a la oficina | BW4: Mayor que cuando iba todos los días a la oficina | BX4: Mayor que cuando iba todos los días a la oficina | BY4: Igual que cuando iba todos los días a la oficina | BZ4: Igual que cuando iba todos los días a la oficina | CA4: Igual que cuando iba todos los días a la oficina | CB4: Igual que cuando iba todos los días a la oficina | CC4: Igual que cuando iba todos los días a la oficina | CD4: Igual que cuando iba todos los días a la oficina | CE4: Igual que cuando iba todos los días a la oficina | CF4: Iguales que cuando iba todos los días a la oficina | CG4: Igual que cuando iba todos los días a la oficina | CH4: Igual que cuando iba todos los días a la oficina | CI4: Igual que cuando iba todos los días a la oficina | CJ4: Igual que cuando iba todos los días a la oficina | CK4: Igual que cuando iba todos los días a la oficina | CL4: Igual que cuando iba todos los días a la oficina | CM4: Igual que cuando iba todos los días a la oficina | CN4: Igual que cuando iba todos los días a la oficina | CO4: Igual que cuando iba todos los días a la oficina | CP4: Igual que cuando iba todos los días a la oficina | CQ4: Igual que cuando iba todos los días a la oficina | CR4: Igual que cuando iba todos los días a la oficina | CS4: Iguales que cuando iba todos los días a la oficina | CT4: Igual que cuando iba todos los días a la oficina | CU4: Igual que cuando iba todos los días a la oficina | CV4: de.escobarc1@uniandes.edu.co | CW4: <301 empleados | CX4: =VLOOKUP(K4,Sheet2!$A$2:$B$58,2,0) -> 0 | CY4: =_xlfn.TEXTJOIN(",",FALSE,A4:CX4) -> 45573,063303044,Colombia,<35 años,Masculino,Profesional,Como empleado de una empresa,Bogotá ,5-10 años,5-10 años,Desarollador junior,Líder técnico de desarrollo,Lulo bank,151-300 empleados,Empresa que desarrolla software a medida partiendo desde cero,Local,Casi Nunca,Alto,>5 días,Ninguno,A integraciones de trabajo,,,,Remota ( todos los días en casa),Impuesta por la empresa,Totalmente en desacuerdo,Igual que cuando iba todos los días a la oficina,Igual que cuando iba todos los días a la oficina,Igual que cuando iba todos los días a la oficina,Iguales que cuando iba todos los días a la oficina,Todas por videoconferencia,Igual que cuando eran en la oficina,Mayor que cuando iba todos los días a la oficina,Mucho Mayor que cuando iba todos los días a la oficina,Mayor que cuando iba todos los días a la oficina,Mayor que cuando iba todos los días a la oficina,Igual que cuando iba todos los días a la oficina,Mejora mi desempeño en el trabajo,Mejoran mi productividad,Igual que cuando iba todos los días a la oficina,Igual que cuando iba todos los días a la oficina,Igual que cuando iba todos los días a la oficina,Igual que cuando iba todos los días a la oficina,Igual que cuando iba todos los días a la oficina,Igual que cuando iba todos los días a la oficina,Igual que cuando iba todos los días a la oficina,Igual que cuando iba todos los días a la oficina,Igual que cuando iba todos los días a la oficina,Igual que cuando iba todos los días a la oficina,Igual que cuando iba todos los días a la oficina,Iguales que cuando iba todos los días a la oficina,Igual que cuando iba todos los días a la oficina,Igual que cuando iba todos los días a la oficina,Igual que cuando iba todos los días a la oficina,Igual que cuando iba todos los días a la oficina,Igual que cuando iba todos los días a la oficina,Igual que cuando iba todos los días a la oficina,Igual que cuando iba todos los días a la oficina,Igual que cuando iba todos los días a la oficina,Iguales que cuando iba todos los días a la oficina,Igual que cuando iba todos los días a la oficina,Iguales que cuando iba todos los días a la oficina,Mayor que cuando iba todos los días a la oficina,Iguales que cuando iba todos los días a la oficina,Iguales que cuando iba todos los días a la oficina,Igual que cuando iba todos los días a la oficina,Igual que cuando iba todos los días a la oficina,Iguales que cuando iba todos los días a la oficina,Igual que cuando iba todos los días a la oficina,Igual que cuando iba todos los días a la oficina,Igual que cuando iba todos los días a la oficina,Iguales que cuando iba todos los días a la oficina,Igual que cuando iba todos los días a la oficina,Igual que cuando iba todos los días a la oficina,Mayor que cuando iba todos los días a la oficina,Mayor que cuando iba todos los días a la oficina,Igual que cuando iba todos los días a la oficina,Igual que cuando iba todos los días a la oficina,Igual que cuando iba todos los días a la oficina,Igual que cuando iba todos los días a la oficina,Igual que cuando iba todos los días a la oficina,Igual que cuando iba todos los días a la oficina,Igual que cuando iba todos los días a la oficina,Iguales que cuando iba todos los días a la oficina,Igual que cuando iba todos los días a la oficina,Igual que cuando iba todos los días a la oficina,Igual que cuando iba todos los días a la oficina,Igual que cuando iba todos los días a la oficina,Igual que cuando iba todos los días a la oficina,Igual que cuando iba todos los días a la oficina,Igual que cuando iba todos los días a la oficina,Igual que cuando iba todos los días a la oficina,Igual que cuando iba todos los días a la oficina,Igual que cuando iba todos los días a la oficina,Igual que cuando iba todos los días a la oficina,Igual que cuando iba todos los días a la oficina,Iguales que cuando iba todos los días a la oficina,Igual que cuando iba todos los días a la oficina,Igual que cuando iba todos los días a la oficina,de.escobarc1@uniandes.edu.co,<301 empleados,0
A5: 45562.001 | B5: Colombia | C5: <35 años | D5: Masculino | E5: Postgrado | F5: Como empleado de una empresa | G5: Colombia | H5: 5-10 años | I5: <5 años | J5: Desarrollador de Software | K5: Tech Lead | L5: Asesoftware | M5: 301-500 empleados | N5: Fábrica de Software | O5: Local | P5: Casi Nunca | Q5: Alto | R5: >5 días | S5: Ninguno | T5: Reuniones con cliente | V5: Reuniones de seguimiento o con cliente | X5: Remota ( todos los días en casa) | Y5: Consensuada por las dos partes | Z5: De acuerdo | AA5: Igual que cuando iba todos los días a la oficina | AB5: Igual que cuando iba todos los días a la oficina | AC5: Igual que cuando iba todos los días a la oficina | AD5: Iguales que cuando iba todos los días a la oficina | AE5: Casi todas por videoconferencia | AF5: Menor que cuando eran en la oficina | AG5: Mayor que cuando iba todos los días a la oficina | AH5: Igual que cuando iba todos los días a la oficina | AI5: Igual que cuando iba todos los días a la oficina | AJ5: Igual que cuando iba todos los días a la oficina | AK5: Mucho Mejor que cuando iba todos los días a la oficina | AL5: Mejora mi desempeño en el trabajo | AM5: No afectan a mi productividad | AN5: Igual que cuando iba todos los días a la oficina | AO5: Menor que cuando iba todos los días a la oficina | AP5: Igual que cuando iba todos los días a la oficina | AQ5: Igual que cuando iba todos los días a la oficina | AR5: No trabajo con personas con un horario distinto al mío | AS5: Igual que cuando iba todos los días a la oficina | AT5: No tengo la información para contestar a la pregunta | AU5: Menos que cuando iba todos los días a la oficina | AV5: Igual que cuando iba todos los días a la oficina | AW5: Igual que cuando iba todos los días a la oficina | AX5: Igual que cuando iba todos los días a la oficina | AY5: Iguales que cuando iba todos los días a la oficina | AZ5: Igual que cuando iba todos los días a la oficina | BA5: Igual que cuando iba todos los días a la oficina | BB5: Menor que cuando iba todos los días a la oficina | BC5: Mayor que cuando iba todos los días a la oficina | BD5: Menor que cuando iba todos los días a la oficina | BE5: Menor que cuando iba todos los días a la oficina | BF5: Igual que cuando iba todos los días a la oficina | BG5: Mucho mayor que cuando iba todos los días a la oficina | BH5: Mucho menores que cuando iba todos los días a la oficina | BI5: Igual que cuando iba todos los días a la oficina | BJ5: No hay diferencias culturales en mi equipo | BK5: Igual que cuando iba todos los días a la oficina | BL5: Iguales que cuando iba todos los días a la oficina | BM5: No tengo que utilizar diferentes idiomas en mi trabajo | BN5: No trabajo con personas con distintos horarios | BO5: Igual que cuando iba todos los días a la oficina | BP5: Mucho menores que cuando iba todos los días a la oficina | BQ5: Mucho mayor que cuando iba todos los días a la oficina | BR5: Igual que cuando iba todos los días a la oficina | BS5: No tengo la información para contestar a la pregunta | BT5: Iguales que cuando iba todos los días a la oficina | BU5: Igual que cuando iba todos los días a la oficina | BV5: Mucho Mayor que cuando iba todos los días a la oficina | BW5: Mucho Mayor que cuando iba todos los días a la oficina | BX5: Mucho mayor que cuando iba todos los días a la oficina | BY5: Mayor que cuando iba todos los días a la oficina | BZ5: Igual que cuando iba todos los días a la oficina | CA5: Mayor que cuando iba todos los días a la oficina | CB5: Mucho Mayor que cuando iba todos los días a la oficina | CC5: Mucho Mayor que cuando iba todos los días a la oficina | CD5: Igual que cuando iba todos los días a la oficina | CE5: Igual que cuando iba todos los días a la oficina | CF5: Menores que cuando iba todos los días a la oficina | CG5: Igual que cuando iba todos los días a la oficina | CH5: Mayor que cuando iba todos los días a la oficina | CI5: Igual que cuando iba todos los días a la oficina | CJ5: Menor que cuando iba todos los días a la oficina | CK5: Igual que cuando iba todos los días a la oficina | CL5: Igual que cuando iba todos los días a la oficina | CM5: Mejor que cuando iba todos los días a la oficina | CN5: Igual que cuando iba todos los días a la oficina | CO5: Igual que cuando iba todos los días a la oficina | CP5: Igual que cuando iba todos los días a la oficina | CQ5: Mucho Mayor que cuando iba todos los días a la oficina | CR5: Mucho menor que cuando iba todos los días a la oficina | CS5: Iguales que cuando iba todos los días a la oficina | CT5: Igual que cuando iba todos los días a la oficina | CU5: Mucho mayor que cuando iba todos los días a la oficina | CV5: xavigonpa@gmail.com | CW5: 301+ empleados | CX5: =VLOOKUP(K5,Sheet2!$A$2:$B$58,2,0) -> 0 | CY5: =_xlfn.TEXTJOIN(",",FALSE,A5:CX5) -> 45562,0007543056,Colombia,<35 años,Masculino,Postgrado,Como empleado de una empresa,Colombia,5-10 años,<5 años,Desarrollador de Software,Tech Lead,Asesoftware,301-500 empleados,Fábrica de Software,Local,Casi Nunca,Alto,>5 días,Ninguno,Reuniones con cliente,,Reuniones de seguimiento o con cliente,,Remota ( todos los días en casa),Consensuada por las dos partes,De acuerdo,Igual que cuando iba todos los días a la oficina,Igual que cuando iba todos los días a la oficina,Igual que cuando iba todos los días a la oficina,Iguales que cuando iba todos los días a la oficina,Casi todas por videoconferencia,Menor que cuando eran en la oficina,Mayor que cuando iba todos los días a la oficina,Igual que cuando iba todos los días a la oficina,Igual que cuando iba todos los días a la oficina,Igual que cuando iba todos los días a la oficina,Mucho Mejor que cuando iba todos los días a la oficina,Mejora mi desempeño en el trabajo,No afectan a mi productividad,Igual que cuando iba todos los días a la oficina,Menor que cuando iba todos los días a la oficina,Igual que cuando iba todos los días a la oficina,Igual que cuando iba todos los días a la oficina,No trabajo con personas con un horario distinto al mío,Igual que cuando iba todos los días a la oficina,No tengo la información para contestar a la pregunta,Menos que cuando iba todos los días a la oficina,Igual que cuando iba todos los días a la oficina,Igual que cuando iba todos los días a la oficina,Igual que cuando iba todos los días a la oficina,Iguales que cuando iba todos los días a la oficina,Igual que cuando iba todos los días a la oficina,Igual que cuando iba todos los días a la oficina,Menor que cuando iba todos los días a la oficina,Mayor que cuando iba todos los días a la oficina,Menor que cuando iba todos los días a la oficina,Menor que cuando iba todos los días a la oficina,Igual que cuando iba todos los días a la oficina,Mucho mayor que cuando iba todos los días a la oficina,Mucho menores que cuando iba todos los días a la oficina,Igual que cuando iba todos los días a la oficina,No hay diferencias culturales en mi equipo,Igual que cuando iba todos los días a la oficina,Iguales que cuando iba todos los días a la oficina,No tengo que utilizar diferentes idiomas en mi trabajo,No trabajo con personas con distintos horarios,Igual que cuando iba todos los días a la oficina,Mucho menores que cuando iba todos los días a la oficina,Mucho mayor que cuando iba todos los días a la oficina,Igual que cuando iba todos los días a la oficina,No tengo la información para contestar a la pregunta,Iguales que cuando iba todos los días a la oficina,Igual que cuando iba todos los días a la oficina,Mucho Mayor que cuando iba todos los días a la oficina,Mucho Mayor que cuando iba todos los días a la oficina,Mucho mayor que cuando iba todos los días a la oficina,Mayor que cuando iba todos los días a la oficina,Igual que cuando iba todos los días a la oficina,Mayor que cuando iba todos los días a la oficina,Mucho Mayor que cuando iba todos los días a la oficina,Mucho Mayor que cuando iba todos los días a la oficina,Igual que cuando iba todos los días a la oficina,Igual que cuando iba todos los días a la oficina,Menores que cuando iba todos los días a la oficina,Igual que cuando iba todos los días a la oficina,Mayor que cuando iba todos los días a la oficina,Igual que cuando iba todos los días a la oficina,Menor que cuando iba todos los días a la oficina,Igual que cuando iba todos los días a la oficina,Igual que cuando iba todos los días a la oficina,Mejor que cuando iba todos los días a la oficina,Igual que cuando iba todos los días a la oficina,Igual que cuando iba todos los días a la oficina,Igual que cuando iba todos los días a la oficina,Mucho Mayor que cuando iba todos los días a la oficina,Mucho menor que cuando iba todos los días a la oficina,Iguales que cuando iba todos los días a la oficina,Igual que cuando iba todos los días a la oficina,Mucho mayor que cuando iba todos los días a la oficina,xavigonpa@gmail.com,301+ empleados,0
A6: 45564.76 | B6: Colombia | C6: <35 años | D6: Masculino | E6: Profesional | F6: Como empleado de una empresa | G6: Colombia | H6: 11-20 años | I6: 5-10 años | J6: Desarrollador Senior y Líder Técnico | K6: Director de Tecnología y Desarrollo de Software | L6: Crediestado | M6: <50 empleados | N6: Empresa que desarrolla software a medida partiendo desde cero | O6: Nacional (múltiples sedes en el mismo país) | P6: Nunca | Q6: Alto | R6: >5 días | S6: Ninguno | T6: No, sin embargo me solicitan ir en momentos extremadamente necesario | W6: Considero que sería complejo, en casa soy feliz y tengo más tiempo para dedicar a mi trabajo y en unos pocos minutos hacer cambio a mis actividades personales. En el caso extremo de tener que asistir a la oficina, esperaría tener una oficina bonita, parqueadero, y una buena cafetería para asistir. | X6: Remota ( todos los días en casa) | Y6: Consensuada por las dos partes | Z6: En desacuerdo | AA6: Mucho mayor que cuando iba todos los días a la oficina | AB6: Mayor que cuando iba todos los días a la oficina | AC6: Igual que cuando iba todos los días a la oficina | AD6: Diferentes que cuando iba todos los días a la oficina, ahora necesito menos horas para hacer lo mismo | AE6: Todas por videoconferencia | AF6: Mucho menor que cuando eran en la oficina | AG6: Mayor que cuando iba todos los días a la oficina | AH6: Mucho Mayor que cuando iba todos los días a la oficina | AI6: Mucho Mayor que cuando iba todos los días a la oficina | AJ6: Mayor que cuando iba todos los días a la oficina | AK6: Igual que cuando iba todos los días a la oficina | AL6: Mejora mi desempeño en el trabajo | AM6: No afectan a mi productividad | AN6: Mayor que cuando iba todos los días a la oficina | AO6: Mucho menor que cuando iba todos los días a la oficina | AP6: Mucho menos que cuando iba todos los días a la oficina | AQ6: No trabajo con personas de distintas culturas | AR6: No trabajo con personas con un horario distinto al mío | AS6: No trabajo con personas que se encuentran geográficamente distribuidas | AT6: Menos que cuando iba todos los días a la oficina | AU6: Menos que cuando iba todos los días a la oficina | AV6: No tengo la información para contestar a la pregunta | AW6: Menos que cuando iba todos los días a la oficina | AX6: Menos que cuando iba todos los días a la oficina | AY6: Mayores que cuando iba todos los días a la oficina | AZ6: Mayor que cuando iba todos los días a la oficina | BA6: Mucho Mayor que cuando iba todos los días a la oficina | BB6: Menor que cuando iba todos los días a la oficina | BC6: Mayor que cuando iba todos los días a la oficina | BD6: Menor que cuando iba todos los días a la oficina | BE6: Menor que cuando iba todos los días a la oficina | BF6: Menor que cuando iba todos los días a la oficina | BG6: Mucho mayor que cuando iba todos los días a la oficina | BH6: Iguales que cuando iba todos los días a la oficina | BI6: Mayor que cuando iba todos los días a la oficina | BJ6: No hay diferencias culturales en mi equipo | BK6: Mayor que cuando iba todos los días a la oficina | BL6: Menores que cuando iba todos los días a la oficina | BM6: No tengo que utilizar diferentes idiomas en mi trabajo | BN6: No trabajo con personas con distintos horarios | BO6: Mucho mayor que cuando iba todos los días a la oficina | BP6: Menores que cuando iba todos los días a la oficina | BQ6: Mucho mayor que cuando iba todos los días a la oficina | BR6: Menor que cuando iba todos los días a la oficina | BS6: Menos que cuando iba todos los días a la oficina | BT6: Menores que cuando iba todos los días a la oficina | BU6: Mejor que cuando iba todos los días a la oficina | BV6: Mucho Mayor que cuando iba todos los días a la oficina | BW6: Mayor que cuando iba todos los días a la oficina | BX6: Mayor que cuando iba todos los días a la oficina | BY6: Igual que cuando iba todos los días a la oficina | BZ6: Igual que cuando iba todos los días a la oficina | CA6: Mayor que cuando iba todos los días a la oficina | CB6: Mucho Mayor que cuando iba todos los días a la oficina | CC6: Mayor que cuando iba todos los días a la oficina | CD6: Menor que cuando iba todos los días a la oficina | CE6: Mas que cuando iba todos los días a la oficina | CF6: Iguales que cuando iba todos los días a la oficina | CG6: Mayor que cuando iba todos los días a la oficina | CH6: Mucho Mayor que cuando iba todos los días a la oficina | CI6: Mayor que cuando iba todos los días a la oficina | CJ6: Mucho menor que cuando iba todos los días a la oficina | CK6: Mayor que cuando iba todos los días a la oficina | CL6: Igual que cuando iba todos los días a la oficina | CM6: Mejor que cuando iba todos los días a la oficina | CN6: Mucho Mayor que cuando iba todos los días a la oficina | CO6: Mayor que cuando iba todos los días a la oficina | CP6: Mayor que cuando iba todos los días a la oficina | CQ6: Mucho Mayor que cuando iba todos los días a la oficina | CR6: Menor que cuando iba todos los días a la oficina | CS6: Menores que cuando iba todos los días a la oficina | CT6: Mucho Mayor que cuando iba todos los días a la oficina | CU6: Mayor que cuando iba todos los días a la oficina | CV6: miguel.vega.ruiz@gmail.com | CW6: <301 empleados | CX6: =VLOOKUP(K6,Sheet2!$A$2:$B$58,2,0) -> 0 | CY6: =_xlfn.TEXTJOIN(",",FALSE,A6:CX6) -> 45564,7603757292,Colombia,<35 años,Masculino,Profesional,Como empleado de una empresa,Colombia,11-20 años,5-10 años,Desarrollador Senior y Líder Técnico,Director de Tecnología y Desarrollo de Software,Crediestado,<50 empleados,Empresa que desarrolla software a medida partiendo desde cero,Nacional (múltiples sedes en el mismo país),Nunca,Alto,>5 días,Ninguno,No, sin embargo me solicitan ir en momentos extremadamente necesario,,,Considero que sería complejo, en casa soy feliz y tengo más tiempo para dedicar a mi trabajo y en unos pocos minutos hacer cambio a mis actividades personales. En el caso extremo de tener que asistir a la oficina, esperaría tener una oficina bonita, parqueadero, y una buena cafetería para asistir.,Remota ( todos los días en casa),Consensuada por las dos partes,En desacuerdo,Mucho mayor que cuando iba todos los días a la oficina,Mayor que cuando iba todos los días a la oficina,Igual que cuando iba todos los días a la oficina,Diferentes que cuando iba todos los días a la oficina, ahora necesito menos horas para hacer lo mismo,Todas por videoconferencia,Mucho menor que cuando eran en la oficina,Mayor que cuando iba todos los días a la oficina,Mucho Mayor que cuando iba todos los días a la oficina,Mucho Mayor que cuando iba todos los días a la oficina,Mayor que cuando iba todos los días a la oficina,Igual que cuando iba todos los días a la oficina,Mejora mi desempeño en el trabajo,No afectan a mi productividad,Mayor que cuando iba todos los días a la oficina,Mucho menor que cuando iba todos los días a la oficina,Mucho menos que cuando iba todos los días a la oficina,No trabajo con personas de distintas culturas,No trabajo con personas con un horario distinto al mío,No trabajo con personas que se encuentran geográficamente distribuidas,Menos que cuando iba todos los días a la oficina,Menos que cuando iba todos los días a la oficina,No tengo la información para contestar a la pregunta,Menos que cuando iba todos los días a la oficina,Menos que cuando iba todos los días a la oficina,Mayores que cuando iba todos los días a la oficina,Mayor que cuando iba todos los días a la oficina,Mucho Mayor que cuando iba todos los días a la oficina,Menor que cuando iba todos los días a la oficina,Mayor que cuando iba todos los días a la oficina,Menor que cuando iba todos los días a la oficina,Menor que cuando iba todos los días a la oficina,Menor que cuando iba todos los días a la oficina,Mucho mayor que cuando iba todos los días a la oficina,Iguales que cuando iba todos los días a la oficina,Mayor que cuando iba todos los días a la oficina,No hay diferencias culturales en mi equipo,Mayor que cuando iba todos los días a la oficina,Menores que cuando iba todos los días a la oficina,No tengo que utilizar diferentes idiomas en mi trabajo,No trabajo con personas con distintos horarios,Mucho mayor que cuando iba todos los días a la oficina,Menores que cuando iba todos los días a la oficina,Mucho mayor que cuando iba todos los días a la oficina,Menor que cuando iba todos los días a la oficina,Menos que cuando iba todos los días a la oficina,Menores que cuando iba todos los días a la oficina,Mejor que cuando iba todos los días a la oficina,Mucho Mayor que cuando iba todos los días a la oficina,Mayor que cuando iba todos los días a la oficina,Mayor que cuando iba todos los días a la oficina,Igual que cuando iba todos los días a la oficina,Igual que cuando iba todos los días a la oficina,Mayor que cuando iba todos los días a la oficina,Mucho Mayor que cuando iba todos los días a la oficina,Mayor que cuando iba todos los días a la oficina,Menor que cuando iba todos los días a la oficina,Mas que cuando iba todos los días a la oficina,Iguales que cuando iba todos los días a la oficina,Mayor que cuando iba todos los días a la oficina,Mucho Mayor que cuando iba todos los días a la oficina,Mayor que cuando iba todos los días a la oficina,Mucho menor que cuando iba todos los días a la oficina,Mayor que cuando iba todos los días a la oficina,Igual que cuando iba todos los días a la oficina,Mejor que cuando iba todos los días a la oficina,Mucho Mayor que cuando iba todos los días a la oficina,Mayor que cuando iba todos los días a la oficina,Mayor que cuando iba todos los días a la oficina,Mucho Mayor que cuando iba todos los días a la oficina,Menor que cuando iba todos los días a la oficina,Menores que cuando iba todos los días a la oficina,Mucho Mayor que cuando iba todos los días a la oficina,Mayor que cuando iba todos los días a la oficina,miguel.vega.ruiz@gmail.com,<301 empleados,0
A7: 45561.741 | B7: Colombia | C7: <35 años | D7: Femenino | E7: Profesional | F7: Como empleado de una empresa | G7: Estado Unidos | H7: 5-10 años | I7: <5 años | J7: Desarrolladora y gerente de ingeniería | K7: Gerente de Ingeniería | M7: >500 empleados. | N7: Fábrica de Software | O7: Multinacional | P7: Muy Frecuentemente | Q7: Alto | R7: >5 días | S7: Ninguno | T7: Trabajo esporádico | U7: Para eventos especiales y reuniones de equipo | V7: Dos veces a la semana a trabajar regularmente | W7: Parqueadero gratuito, mejora en bono alimenticio y horario flexible | X7: Remota ( todos los días en casa) | Y7: Consensuada por las dos partes | Z7: De acuerdo | AA7: Menor que cuando iba todos los días a la oficina | AB7: Igual que cuando iba todos los días a la oficina | AC7: Menor que cuando iba todos los días a la oficina | AD7: Iguales que cuando iba todos los días a la oficina | AE7: Todas por videoconferencia | AF7: Igual que cuando eran en la oficina | AG7: Igual que cuando iba todos los días a la oficina | AH7: Igual que cuando iba todos los días a la oficina | AI7: Igual que cuando iba todos los días a la oficina | AJ7: Menor que cuando iba todos los días a la oficina | AK7: Menor que cuando iba todos los días a la oficina | AL7: Negativamente a la hora de desempeñar mi trabajo | AM7: Mejoran mi productividad | AN7: Menor que cuando iba todos los días a la oficina | AO7: Igual que cuando iba todos los días a la oficina | AP7: No tengo la información para contestar a la pregunta | AQ7: Igual que cuando iba todos los días a la oficina | AR7: Menos que cuando iba todos los días a la oficina | AS7: Menos que cuando iba todos los días a la oficina | AT7: Más que cuando iba todos los días a la oficina | AU7: Igual que cuando iba todos los días a la oficina | AV7: Mas que cuando iba todos los días a la oficina | AW7: Mas que cuando iba todos los días a la oficina | AX7: Mas que cuando iba todos los días a la oficina | AY7: Menores que cuando iba todos los días a la oficina | AZ7: Menor que cuando iba todos los días a la oficina | BA7: Igual que cuando iba todos los días a la oficina | BB7: Mayor que cuando iba todos los días a la oficina | BC7: Mayor que cuando iba todos los días a la oficina | BD7: Mayor que cuando iba todos los días a la oficina | BE7: Mayor que cuando iba todos los días a la oficina | BF7: Igual que cuando iba todos los días a la oficina | BG7: Mayor que cuando iba todos los días a la oficina | BH7: Iguales que cuando iba todos los días a la oficina | BI7: Igual que cuando iba todos los días a la oficina | BJ7: Iguales que cuando iba todos los días a la oficina | BK7: Igual que cuando iba todos los días a la oficina | BL7: Mayores que cuando iba todos los días a la oficina | BM7: Iguales que cuando iba todos los días a la oficina | BN7: Igual que cuando iba todos los días a la oficina | BO7: Menor que cuando iba todos los días a la oficina | BP7: Mayores que cuando iba todos los días a la oficina | BQ7: Menor que cuando iba todos los días a la oficina | BR7: Mayor que cuando iba todos los días a la oficina | BS7: Más que cuando iba todos los días a la oficina | BT7: Iguales que cuando iba todos los días a la oficina | BU7: Igual que cuando iba todos los días a la oficina | BV7: Menor que cuando iba todos los días a la oficina | BW7: Menor que cuando iba todos los días a la oficina | BX7: Mayor que cuando iba todos los días a la oficina | BY7: Igual que cuando iba todos los días a la oficina | BZ7: Igual que cuando iba todos los días a la oficina | CA7: Igual que cuando iba todos los días a la oficina | CB7: Menor que cuando iba todos los días a la oficina | CC7: Menor que cuando iba todos los días a la oficina | CD7: Igual que cuando iba todos los días a la oficina | CE7: Menos que cuando iba todos los días a la oficina | CF7: Iguales que cuando iba todos los días a la oficina | CG7: Igual que cuando iba todos los días a la oficina | CH7: Mayor que cuando iba todos los días a la oficina | CI7: Menor que cuando iba todos los días a la oficina | CJ7: Mayor que cuando iba todos los días a la oficina | CK7: Menor que cuando iba todos los días a la oficina | CL7: Mayor que cuando iba todos los días a la oficina | CM7: Peor que cuando iba todos los días a la oficina | CN7: Menor que cuando iba todos los días a la oficina | CO7: Menor que cuando iba todos los días a la oficina | CP7: Igual que cuando iba todos los días a la oficina | CQ7: Igual que cuando iba todos los días a la oficina | CR7: Igual que cuando iba todos los días a la oficina | CS7: Mayores que cuando iba todos los días a la oficina | CT7: Mucho menor que cuando iba todos los días a la oficina | CU7: Menor que cuando iba todos los días a la oficina | CW7: 301+ empleados | CX7: =VLOOKUP(K7,Sheet2!$A$2:$B$58,2,0) -> 0 | CY7: =_xlfn.TEXTJOIN(",",FALSE,A7:CX7) -> 45561,7409255093,Colombia,<35 años,Femenino,Profesional,Como empleado de una empresa,Estado Unidos,5-10 años,<5 años,Desarrolladora y gerente de ingeniería,Gerente de Ingeniería ,,>500 empleados.,Fábrica de Software,Multinacional,Muy Frecuentemente,Alto,>5 días,Ninguno,Trabajo esporádico ,Para eventos especiales y reuniones de equipo,Dos veces a la semana a trabajar regularmente,Parqueadero gratuito, mejora en bono alimenticio y horario flexible,Remota ( todos los días en casa),Consensuada por las dos partes,De acuerdo,Menor que cuando iba todos los días a la oficina,Igual que cuando iba todos los días a la oficina,Menor que cuando iba todos los días a la oficina,Iguales que cuando iba todos los días a la oficina,Todas por videoconferencia,Igual que cuando eran en la oficina,Igual que cuando iba todos los días a la oficina,Igual que cuando iba todos los días a la oficina,Igual que cuando iba todos los días a la oficina,Menor que cuando iba todos los días a la oficina,Menor que cuando iba todos los días a la oficina,Negativamente a la hora de desempeñar mi trabajo,Mejoran mi productividad,Menor que cuando iba todos los días a la oficina,Igual que cuando iba todos los días a la oficina,No tengo la información para contestar a la pregunta,Igual que cuando iba todos los días a la oficina,Menos que cuando iba todos los días a la oficina,Menos que cuando iba todos los días a la oficina,Más que cuando iba todos los días a la oficina,Igual que cuando iba todos los días a la oficina,Mas que cuando iba todos los días a la oficina,Mas que cuando iba todos los días a la oficina,Mas que cuando iba todos los días a la oficina,Menores que cuando iba todos los días a la oficina,Menor que cuando iba todos los días a la oficina,Igual que cuando iba todos los días a la oficina,Mayor que cuando iba todos los días a la oficina,Mayor que cuando iba todos los días a la oficina,Mayor que cuando iba todos los días a la oficina,Mayor que cuando iba todos los días a la oficina,Igual que cuando iba todos los días a la oficina,Mayor que cuando iba todos los días a la oficina,Iguales que cuando iba todos los días a la oficina,Igual que cuando iba todos los días a la oficina,Iguales que cuando iba todos los días a la oficina,Igual que cuando iba todos los días a la oficina,Mayores que cuando iba todos los días a la oficina,Iguales que cuando iba todos los días a la oficina,Igual que cuando iba todos los días a la oficina,Menor que cuando iba todos los días a la oficina,Mayores que cuando iba todos los días a la oficina,Menor que cuando iba todos los días a la oficina,Mayor que cuando iba todos los días a la oficina,Más que cuando iba todos los días a la oficina,Iguales que cuando iba todos los días a la oficina,Igual que cuando iba todos los días a la oficina,Menor que cuando iba todos los días a la oficina,Menor que cuando iba todos los días a la oficina,Mayor que cuando iba todos los días a la oficina,Igual que cuando iba todos los días a la oficina,Igual que cuando iba todos los días a la oficina,Igual que cuando iba todos los días a la oficina,Menor que cuando iba todos los días a la oficina,Menor que cuando iba todos los días a la oficina,Igual que cuando iba todos los días a la oficina,Menos que cuando iba todos los días a la oficina,Iguales que cuando iba todos los días a la oficina,Igual que cuando iba todos los días a la oficina,Mayor que cuando iba todos los días a la oficina,Menor que cuando iba todos los días a la oficina,Mayor que cuando iba todos los días a la oficina,Menor que cuando iba todos los días a la oficina,Mayor que cuando iba todos los días a la oficina,Peor que cuando iba todos los días a la oficina,Menor que cuando iba todos los días a la oficina,Menor que cuando iba todos los días a la oficina,Igual que cuando iba todos los días a la oficina,Igual que cuando iba todos los días a la oficina,Igual que cuando iba todos los días a la oficina,Mayores que cuando iba todos los días a la oficina,Mucho menor que cuando iba todos los días a la oficina,Menor que cuando iba todos los días a la oficina,,301+ empleados,0
A8: 45564.733 | B8: Colombia | C8: <35 años | D8: Masculino | E8: Maestria - Terminando | F8: Como empleado de una empresa | G8: Colombia | H8: 5-10 años | I8: <5 años | J8: Developer | K8: Líder Técnico | M8: >500 empleados. | N8: Empresa que desarrolla software a medida partiendo desde cero | O8: Nacional (múltiples sedes en el mismo país) | P8: Nunca | Q8: Alto | R8: >5 días | S8: Ninguno | T8: Reuniones del área, reuniones con clientes, recibir o entregar dispositivos | V8: Reuniones | W8: Nada | X8: Híbrida casa (más días en casa que en la oficina) | Y8: Impuesta por la empresa | Z8: En desacuerdo | AA8: Menor que cuando iba todos los días a la oficina | AB8: Menor que cuando iba todos los días a la oficina | AC8: Menor que cuando iba todos los días a la oficina | AD8: Diferentes que cuando iba todos los días a la oficina, ahora necesito menos horas para hacer lo mismo | AE8: Casi todas por videoconferencia | AF8: Mucho menor que cuando eran en la oficina | AG8: Mayor que cuando iba todos los días a la oficina | AH8: Menor que cuando iba todos los días a la oficina | AI8: Mayor que cuando iba todos los días a la oficina | AJ8: Mucho Mayor que cuando iba todos los días a la oficina | AK8: Mucho Mejor que cuando iba todos los días a la oficina | AL8: Mejora mucho mi desempeño en el trabajo | AM8: Disminuyen mi productividad | AN8: Menor que cuando iba todos los días a la oficina | AO8: Mayor que cuando iba todos los días a la oficina | AP8: Mucho más que cuando iba todos los días a la oficina | AQ8: No trabajo con personas de distintas culturas | AR8: No trabajo con personas con un horario distinto al mío | AS8: No trabajo con personas que se encuentran geográficamente distribuidas | AT8: Mucho más que cuando iba todos los días a la oficina | AU8: Mas que cuando iba todos los días a la oficina | AV8: Mas que cuando iba todos los días a la oficina | AW8: Mas que cuando iba todos los días a la oficina | AX8: Mas que cuando iba todos los días a la oficina | AY8: Menores que cuando iba todos los días a la oficina | AZ8: Mayor que cuando iba todos los días a la oficina | BA8: Igual que cuando iba todos los días a la oficina | BB8: Mucho menor que cuando iba todos los días a la oficina | BC8: Mayor que cuando iba todos los días a la oficina | BD8: Menor que cuando iba todos los días a la oficina | BE8: Menor que cuando iba todos los días a la oficina | BF8: Menor que cuando iba todos los días a la oficina | BG8: Mayor que cuando iba todos los días a la oficina | BH8: Mucho menores que cuando iba todos los días a la oficina | BI8: Mucho mayor que cuando iba todos los días a la oficina | BJ8: No hay diferencias culturales en mi equipo | BK8: Mucho menor que cuando iba todos los días a la oficina | BL8: Mucho mayores que cuando iba todos los días a la oficina | BM8: No tengo que utilizar diferentes idiomas en mi trabajo | BN8: No trabajo con personas con distintos horarios | BO8: Menor que cuando iba todos los días a la oficina | BP8: Menores que cuando iba todos los días a la oficina | BQ8: Mayor que cuando iba todos los días a la oficina | BR8: Mucho mayor que cuando iba todos los días a la oficina | BS8: Más que cuando iba todos los días a la oficina | BT8: Mucho mayores que cuando iba todos los días a la oficina | BU8: Mejor que cuando iba todos los días a la oficina | BV8: Mayor que cuando iba todos los días a la oficina | BW8: Mucho Mayor que cuando iba todos los días a la oficina | BX8: Mucho mayor que cuando iba todos los días a la oficina | BY8: Igual que cuando iba todos los días a la oficina | BZ8: Mayor que cuando iba todos los días a la oficina | CA8: Mayor que cuando iba todos los días a la oficina | CB8: Mayor que cuando iba todos los días a la oficina | CC8: Mayor que cuando iba todos los días a la oficina | CD8: Menor que cuando iba todos los días a la oficina | CE8: Igual que cuando iba todos los días a la oficina | CF8: Mucho menores que cuando iba todos los días a la oficina | CG8: Menor que cuando iba todos los días a la oficina | CH8: Mayor que cuando iba todos los días a la oficina | CI8: Mucho menor que cuando iba todos los días a la oficina | CJ8: Mucho menor que cuando iba todos los días a la oficina | CK8: Menor que cuando iba todos los días a la oficina | CL8: Mucho menor que cuando iba todos los días a la oficina | CM8: Peor que cuando iba todos los días a la oficina | CN8: Mayor que cuando iba todos los días a la oficina | CO8: Mucho menor que cuando iba todos los días a la oficina | CP8: Menor que cuando iba todos los días a la oficina | CQ8: Menor que cuando iba todos los días a la oficina | CR8: Mucho menor que cuando iba todos los días a la oficina | CS8: Mayores que cuando iba todos los días a la oficina | CT8: Mayor que cuando iba todos los días a la oficina | CU8: Mucho mayor que cuando iba todos los días a la oficina | CV8: na.rodriguez2@uniandes.edu.co | CW8: 301+ empleados | CX8: =VLOOKUP(K8,Sheet2!$A$2:$B$58,2,0) -> 0 | CY8: =_xlfn.TEXTJOIN(",",FALSE,A8:CX8) -> 45564,7333723032,Colombia,<35 años,Masculino,Maestria - Terminando ,Como empleado de una empresa,Colombia,5-10 años,<5 años,Developer,Líder Técnico,,>500 empleados.,Empresa que desarrolla software a medida partiendo desde cero,Nacional (múltiples sedes en el mismo país),Nunca,Alto,>5 días,Ninguno,Reuniones del área, reuniones con clientes, recibir o entregar dispositivos,,Reuniones,Nada,Híbrida casa (más días en casa que en la oficina),Impuesta por la empresa,En desacuerdo,Menor que cuando iba todos los días a la oficina,Menor que cuando iba todos los días a la oficina,Menor que cuando iba todos los días a la oficina,Diferentes que cuando iba todos los días a la oficina, ahora necesito menos horas para hacer lo mismo,Casi todas por videoconferencia,Mucho menor que cuando eran en la oficina,Mayor que cuando iba todos los días a la oficina,Menor que cuando iba todos los días a la oficina,Mayor que cuando iba todos los días a la oficina,Mucho Mayor que cuando iba todos los días a la oficina,Mucho Mejor que cuando iba todos los días a la oficina,Mejora mucho mi desempeño en el trabajo,Disminuyen mi productividad,Menor que cuando iba todos los días a la oficina,Mayor que cuando iba todos los días a la oficina,Mucho más que cuando iba todos los días a la oficina,No trabajo con personas de distintas culturas,No trabajo con personas con un horario distinto al mío,No trabajo con personas que se encuentran geográficamente distribuidas,Mucho más que cuando iba todos los días a la oficina,Mas que cuando iba todos los días a la oficina,Mas que cuando iba todos los días a la oficina,Mas que cuando iba todos los días a la oficina,Mas que cuando iba todos los días a la oficina,Menores que cuando iba todos los días a la oficina,Mayor que cuando iba todos los días a la oficina,Igual que cuando iba todos los días a la oficina,Mucho menor que cuando iba todos los días a la oficina,Mayor que cuando iba todos los días a la oficina,Menor que cuando iba todos los días a la oficina,Menor que cuando iba todos los días a la oficina,Menor que cuando iba todos los días a la oficina,Mayor que cuando iba todos los días a la oficina,Mucho menores que cuando iba todos los días a la oficina,Mucho mayor que cuando iba todos los días a la oficina,No hay diferencias culturales en mi equipo,Mucho menor que cuando iba todos los días a la oficina,Mucho mayores que cuando iba todos los días a la oficina,No tengo que utilizar diferentes idiomas en mi trabajo,No trabajo con personas con distintos horarios,Menor que cuando iba todos los días a la oficina,Menores que cuando iba todos los días a la oficina,Mayor que cuando iba todos los días a la oficina,Mucho mayor que cuando iba todos los días a la oficina,Más que cuando iba todos los días a la oficina,Mucho mayores que cuando iba todos los días a la oficina,Mejor que cuando iba todos los días a la oficina,Mayor que cuando iba todos los días a la oficina,Mucho Mayor que cuando iba todos los días a la oficina,Mucho mayor que cuando iba todos los días a la oficina,Igual que cuando iba todos los días a la oficina,Mayor que cuando iba todos los días a la oficina,Mayor que cuando iba todos los días a la oficina,Mayor que cuando iba todos los días a la oficina,Mayor que cuando iba todos los días a la oficina,Menor que cuando iba todos los días a la oficina,Igual que cuando iba todos los días a la oficina,Mucho menores que cuando iba todos los días a la oficina,Menor que cuando iba todos los días a la oficina,Mayor que cuando iba todos los días a la oficina,Mucho menor que cuando iba todos los días a la oficina,Mucho menor que cuando iba todos los días a la oficina,Menor que cuando iba todos los días a la oficina,Mucho menor que cuando iba todos los días a la oficina,Peor que cuando iba todos los días a la oficina,Mayor que cuando iba todos los días a la oficina,Mucho menor que cuando iba todos los días a la oficina,Menor que cuando iba todos los días a la oficina,Menor que cuando iba todos los días a la oficina,Mucho menor que cuando iba todos los días a la oficina,Mayores que cuando iba todos los días a la oficina,Mayor que cuando iba todos los días a la oficina,Mucho mayor que cuando iba todos los días a la oficina,na.rodriguez2@uniandes.edu.co,301+ empleados,0
A9: 45574.107 | B9: Colombia | C9: <35 años | D9: Masculino | E9: Maestría | F9: Como empleado de una empresa | G9: Bogotá | H9: 11-20 años | I9: 10-20 años | J9: Gerente general | K9: Gerente general | L9: Sinerware | M9: <50 empleados | N9: Fábrica de Software | O9: Local | P9: Casi Nunca | Q9: Alto | R9: >5 días | S9: Ninguno | T9: Eventos de aprendizaje o comerciales | X9: Remota ( todos los días en casa) | Y9: Consensuada por las dos partes | Z9: En desacuerdo | AA9: Igual que cuando iba todos los días a la oficina | AB9: Menor que cuando iba todos los días a la oficina | AC9: Igual que cuando iba todos los días a la oficina | AD9: Diferentes que cuando iba todos los días a la oficina, ahora necesito menos horas para hacer lo mismo | AE9: Casi todas por videoconferencia | AF9: Menor que cuando eran en la oficina | AG9: Menor cuando iba todos los días a la oficina | AH9: Menor que cuando iba todos los días a la oficina | AI9: Menor que cuando iba todos los días a la oficina | AJ9: Igual que cuando iba todos los días a la oficina | AK9: Mayor que cuando iba todos los días a la oficina | AL9: Mejora mi desempeño en el trabajo | AM9: Mejoran mi productividad | AN9: Igual que cuando iba todos los días a la oficina | AO9: Mayor que cuando iba todos los días a la oficina | AP9: Más que cuando iba todos los días a la oficina | AQ9: No trabajo con personas de distintas culturas | AR9: No trabajo con personas con un horario distinto al mío | AS9: Igual que cuando iba todos los días a la oficina | AT9: Más que cuando iba todos los días a la oficina | AU9: Igual que cuando iba todos los días a la oficina | AV9: Igual que cuando iba todos los días a la oficina | AW9: Igual que cuando iba todos los días a la oficina | AX9: Igual que cuando iba todos los días a la oficina | AY9: Mayores que cuando iba todos los días a la oficina | AZ9: Igual que cuando iba todos los días a la oficina | BA9: Igual que cuando iba todos los días a la oficina | BB9: Menor que cuando iba todos los días a la oficina | BC9: Igual que cuando iba todos los días a la oficina | BD9: Menor que cuando iba todos los días a la oficina | BE9: Igual que cuando iba todos los días a la oficina | BF9: Menor que cuando iba todos los días a la oficina | BG9: Mucho mayor que cuando iba todos los días a la oficina | BH9: Menores que cuando iba todos los días a la oficina | BI9: Mucho mayor que cuando iba todos los días a la oficina | BJ9: No hay diferencias culturales en mi equipo | BK9: Mayor que cuando iba todos los días a la oficina | BL9: Mayores que cuando iba todos los días a la oficina | BM9: No tengo que utilizar diferentes idiomas en mi trabajo | BN9: No trabajo con personas con distintos horarios | BO9: Menor que cuando iba todos los días a la oficina | BP9: Mucho menores que cuando iba todos los días a la oficina | BQ9: Mayor que cuando iba todos los días a la oficina | BR9: Igual que cuando iba todos los días a la oficina | BS9: Igual que cuando iba todos los días a la oficina | BT9: Iguales que cuando iba todos los días a la oficina | BU9: Mejor que cuando iba todos los días a la oficina | BV9: Mayor que cuando iba todos los días a la oficina | BW9: Menor que cuando iba todos los días a la oficina | BX9: Mayor que cuando iba todos los días a la oficina | BY9: Igual que cuando iba todos los días a la oficina | BZ9: Igual que cuando iba todos los días a la oficina | CA9: Igual que cuando iba todos los días a la oficina | CB9: Mayor que cuando iba todos los días a la oficina | CC9: Igual que cuando iba todos los días a la oficina | CD9: Igual que cuando iba todos los días a la oficina | CE9: Igual que cuando iba todos los días a la oficina | CF9: Menores que cuando iba todos los días a la oficina | CG9: Igual que cuando iba todos los días a la oficina | CH9: Menor que cuando iba todos los días a la oficina | CI9: Mayor que cuando iba todos los días a la oficina | CJ9: Menor que cuando iba todos los días a la oficina | CK9: Menor que cuando iba todos los días a la oficina | CL9: Igual que cuando iba todos los días a la oficina | CM9: Igual que cuando iba todos los días a la oficina | CN9: Igual que cuando iba todos los días a la oficina | CO9: Mucho menor que cuando iba todos los días a la oficina | CP9: Igual que cuando iba todos los días a la oficina | CQ9: Mayor que cuando iba todos los días a la oficina | CR9: Menor que cuando iba todos los días a la oficina | CS9: Iguales que cuando iba todos los días a la oficina | CT9: Igual que cuando iba todos los días a la oficina | CU9: Igual que cuando iba todos los días a la oficina | CV9: gcarrillo@sinerware.com | CW9: <301 empleados | CX9: =VLOOKUP(K9,Sheet2!$A$2:$B$58,2,0) -> 1 | CY9: =_xlfn.TEXTJOIN(",",FALSE,A9:CX9) -> 45574,1073788889,Colombia,<35 años,Masculino,Maestría,Como empleado de una empresa,Bogotá,11-20 años,10-20 años,Gerente general,Gerente general,Sinerware,<50 empleados,Fábrica de Software,Local,Casi Nunca,Alto,>5 días,Ninguno,Eventos de aprendizaje o comerciales,,,,Remota ( todos los días en casa),Consensuada por las dos partes,En desacuerdo,Igual que cuando iba todos los días a la oficina,Menor que cuando iba todos los días a la oficina,Igual que cuando iba todos los días a la oficina,Diferentes que cuando iba todos los días a la oficina, ahora necesito menos horas para hacer lo mismo,Casi todas por videoconferencia,Menor que cuando eran en la oficina,Menor cuando iba todos los días a la oficina,Menor que cuando iba todos los días a la oficina,Menor que cuando iba todos los días a la oficina,Igual que cuando iba todos los días a la oficina,Mayor que cuando iba todos los días a la oficina,Mejora mi desempeño en el trabajo,Mejoran mi productividad,Igual que cuando iba todos los días a la oficina,Mayor que cuando iba todos los días a la oficina,Más que cuando iba todos los días a la oficina,No trabajo con personas de distintas culturas,No trabajo con personas con un horario distinto al mío,Igual que cuando iba todos los días a la oficina,Más que cuando iba todos los días a la oficina,Igual que cuando iba todos los días a la oficina,Igual que cuando iba todos los días a la oficina,Igual que cuando iba todos los días a la oficina,Igual que cuando iba todos los días a la oficina,Mayores que cuando iba todos los días a la oficina,Igual que cuando iba todos los días a la oficina,Igual que cuando iba todos los días a la oficina,Menor que cuando iba todos los días a la oficina,Igual que cuando iba todos los días a la oficina,Menor que cuando iba todos los días a la oficina,Igual que cuando iba todos los días a la oficina,Menor que cuando iba todos los días a la oficina,Mucho mayor que cuando iba todos los días a la oficina,Menores que cuando iba todos los días a la oficina,Mucho mayor que cuando iba todos los días a la oficina,No hay diferencias culturales en mi equipo,Mayor que cuando iba todos los días a la oficina,Mayores que cuando iba todos los días a la oficina,No tengo que utilizar diferentes idiomas en mi trabajo,No trabajo con personas con distintos horarios,Menor que cuando iba todos los días a la oficina,Mucho menores que cuando iba todos los días a la oficina,Mayor que cuando iba todos los días a la oficina,Igual que cuando iba todos los días a la oficina,Igual que cuando iba todos los días a la oficina,Iguales que cuando iba todos los días a la oficina,Mejor que cuando iba todos los días a la oficina,Mayor que cuando iba todos los días a la oficina,Menor que cuando iba todos los días a la oficina,Mayor que cuando iba todos los días a la oficina,Igual que cuando iba todos los días a la oficina,Igual que cuando iba todos los días a la oficina,Igual que cuando iba todos los días a la oficina,Mayor que cuando iba todos los días a la oficina,Igual que cuando iba todos los días a la oficina,Igual que cuando iba todos los días a la oficina,Igual que cuando iba todos los días a la oficina,Menores que cuando iba todos los días a la oficina,Igual que cuando iba todos los días a la oficina,Menor que cuando iba todos los días a la oficina,Mayor que cuando iba todos los días a la oficina,Menor que cuando iba todos los días a la oficina,Menor que cuando iba todos los días a la oficina,Igual que cuando iba todos los días a la oficina,Igual que cuando iba todos los días a la oficina,Igual que cuando iba todos los días a la oficina,Mucho menor que cuando iba todos los días a la oficina,Igual que cuando iba todos los días a la oficina,Mayor que cuando iba todos los días a la oficina,Menor que cuando iba todos los días a la oficina,Iguales que cuando iba todos los días a la oficina,Igual que cuando iba todos los días a la oficina,Igual que cuando iba todos los días a la oficina,gcarrillo@sinerware.com,<301 empleados,1
A10: 45573.03 | B10: Colombia | C10: <35 años | D10: Masculino | E10: Posgrado | F10: De ambas formas | G10: Japon | H10: 21-30 años | I10: 10-20 años | J10: Technical Manager | K10: Technical Manager | L10: GlobalLogic | M10: >500 empleados. | N10: Empresa que desarrolla software a medida partiendo desde cero | O10: Multinacional | P10: Muy Frecuentemente | Q10: Alto | R10: >5 días | S10: Ninguno | T10: Eventos de Integración | U10: N/A | V10: N/A | W10: Ninguna | X10: Remota ( todos los días en casa) | Y10: Consensuada por las dos partes | Z10: Totalmente en desacuerdo | AA10: Mucho menor que cuando iba todos los días a la oficina | AB10: Menor que cuando iba todos los días a la oficina | AC10: Menor que cuando iba todos los días a la oficina | AD10: Diferentes que cuando iba todos los días a la oficina, ahora necesito menos horas para hacer lo mismo | AE10: Todas por videoconferencia | AF10: Mayor que cuando eran en la oficina | AG10: Menor cuando iba todos los días a la oficina | AH10: Mayor que cuando iba todos los días a la oficina | AI10: Mayor que cuando iba todos los días a la oficina | AJ10: Menor que cuando iba todos los días a la oficina | AK10: Mucho Mejor que cuando iba todos los días a la oficina | AL10: Mejora mi desempeño en el trabajo | AM10: No afectan a mi productividad | AN10: Igual que cuando iba todos los días a la oficina | AO10: Mayor que cuando iba todos los días a la oficina | AP10: Mucho más que cuando iba todos los días a la oficina | AQ10: Igual que cuando iba todos los días a la oficina | AR10: Igual que cuando iba todos los días a la oficina | AS10: Igual que cuando iba todos los días a la oficina | AT10: Más que cuando iba todos los días a la oficina | AU10: Mas que cuando iba todos los días a la oficina | AV10: Mucho más que cuando iba todos los días a la oficina | AW10: Mas que cuando iba todos los días a la oficina | AX10: Igual que cuando iba todos los días a la oficina | AY10: Iguales que cuando iba todos los días a la oficina | AZ10: Mayor que cuando iba todos los días a la oficina | BA10: Menor que cuando iba todos los días a la oficina | BB10: Mayor que cuando iba todos los días a la oficina | BC10: Mayor que cuando iba todos los días a la oficina | BD10: Menor que cuando iba todos los días a la oficina | BE10: Igual que cuando iba todos los días a la oficina | BF10: Igual que cuando iba todos los días a la oficina | BG10: Mucho mayor que cuando iba todos los días a la oficina | BH10: Menores que cuando iba todos los días a la oficina | BI10: Igual que cuando iba todos los días a la oficina | BJ10: Iguales que cuando iba todos los días a la oficina | BK10: Mayor que cuando iba todos los días a la oficina | BL10: Iguales que cuando iba todos los días a la oficina | BM10: Iguales que cuando iba todos los días a la oficina | BN10: Igual que cuando iba todos los días a la oficina | BO10: Igual que cuando iba todos los días a la oficina | BP10: Mayores que cuando iba todos los días a la oficina | BQ10: Mucho mayor que cuando iba todos los días a la oficina | BR10: Mayor que cuando iba todos los días a la oficina | BS10: Más que cuando iba todos los días a la oficina | BT10: Iguales que cuando iba todos los días a la oficina | BU10: Mejor que cuando iba todos los días a la oficina | BV10: Menor que cuando iba todos los días a la oficina | BW10: Mucho menor que cuando iba todos los días a la oficina | BX10: Mayor que cuando iba todos los días a la oficina | BY10: Igual que cuando iba todos los días a la oficina | BZ10: Igual que cuando iba todos los días a la oficina | CA10: Mayor que cuando iba todos los días a la oficina | CB10: Igual que cuando iba todos los días a la oficina | CC10: Igual que cuando iba todos los días a la oficina | CD10: Mayor que cuando iba todos los días a la oficina | CE10: Igual que cuando iba todos los días a la oficina | CF10: Iguales que cuando iba todos los días a la oficina | CG10: Mayor que cuando iba todos los días a la oficina | CH10: Mayor que cuando iba todos los días a la oficina | CI10: Mucho menor que cuando iba todos los días a la oficina | CJ10: Mayor que cuando iba todos los días a la oficina | CK10: Igual que cuando iba todos los días a la oficina | CL10: Menor que cuando iba todos los días a la oficina | CM10: Igual que cuando iba todos los días a la oficina | CN10: Mayor que cuando iba todos los días a la oficina | CO10: Mucho menor que cuando iba todos los días a la oficina | CP10: Menor que cuando iba todos los días a la oficina | CQ10: Mayor que cuando iba todos los días a la oficina | CR10: Mucho menor que cuando iba todos los días a la oficina | CS10: Menores que cuando iba todos los días a la oficina | CT10: Igual que cuando iba todos los días a la oficina | CU10: Mayor que cuando iba todos los días a la oficina | CV10: dxcorzo@gmail.com | CW10: 301+ empleados | CX10: =VLOOKUP(K10,Sheet2!$A$2:$B$58,2,0) -> 0 | CY10: =_xlfn.TEXTJOIN(",",FALSE,A10:CX10) -> 45573,0299356829,Colombia,<35 años,Masculino,Posgrado,De ambas formas,Japon,21-30 años,10-20 años,Technical Manager,Technical Manager,GlobalLogic,>500 empleados.,Empresa que desarrolla software a medida partiendo desde cero,Multinacional,Muy Frecuentemente,Alto,>5 días,Ninguno,Eventos de Integración,N/A,N/A,Ninguna,Remota ( todos los días en casa),Consensuada por las dos partes,Totalmente en desacuerdo,Mucho menor que cuando iba todos los días a la oficina,Menor que cuando iba todos los días a la oficina,Menor que cuando iba todos los días a la oficina,Diferentes que cuando iba todos los días a la oficina, ahora necesito menos horas para hacer lo mismo,Todas por videoconferencia,Mayor que cuando eran en la oficina,Menor cuando iba todos los días a la oficina,Mayor que cuando iba todos los días a la oficina,Mayor que cuando iba todos los días a la oficina,Menor que cuando iba todos los días a la oficina,Mucho Mejor que cuando iba todos los días a la oficina,Mejora mi desempeño en el trabajo,No afectan a mi productividad,Igual que cuando iba todos los días a la oficina,Mayor que cuando iba todos los días a la oficina,Mucho más que cuando iba todos los días a la oficina,Igual que cuando iba todos los días a la oficina,Igual que cuando iba todos los días a la oficina,Igual que cuando iba todos los días a la oficina,Más que cuando iba todos los días a la oficina,Mas que cuando iba todos los días a la oficina,Mucho más que cuando iba todos los días a la oficina,Mas que cuando iba todos los días a la oficina,Igual que cuando iba todos los días a la oficina,Iguales que cuando iba todos los días a la oficina,Mayor que cuando iba todos los días a la oficina,Menor que cuando iba todos los días a la oficina,Mayor que cuando iba todos los días a la oficina,Mayor que cuando iba todos los días a la oficina,Menor que cuando iba todos los días a la oficina,Igual que cuando iba todos los días a la oficina,Igual que cuando iba todos los días a la oficina,Mucho mayor que cuando iba todos los días a la oficina,Menores que cuando iba todos los días a la oficina,Igual que cuando iba todos los días a la oficina,Iguales que cuando iba todos los días a la oficina,Mayor que cuando iba todos los días a la oficina,Iguales que cuando iba todos los días a la oficina,Iguales que cuando iba todos los días a la oficina,Igual que cuando iba todos los días a la oficina,Igual que cuando iba todos los días a la oficina,Mayores que cuando iba todos los días a la oficina,Mucho mayor que cuando iba todos los días a la oficina,Mayor que cuando iba todos los días a la oficina,Más que cuando iba todos los días a la oficina,Iguales que cuando iba todos los días a la oficina,Mejor que cuando iba todos los días a la oficina,Menor que cuando iba todos los días a la oficina,Mucho menor que cuando iba todos los días a la oficina,Mayor que cuando iba todos los días a la oficina,Igual que cuando iba todos los días a la oficina,Igual que cuando iba todos los días a la oficina,Mayor que cuando iba todos los días a la oficina,Igual que cuando iba todos los días a la oficina,Igual que cuando iba todos los días a la oficina,Mayor que cuando iba todos los días a la oficina,Igual que cuando iba todos los días a la oficina,Iguales que cuando iba todos los días a la oficina,Mayor que cuando iba todos los días a la oficina,Mayor que cuando iba todos los días a la oficina,Mucho menor que cuando iba todos los días a la oficina,Mayor que cuando iba todos los días a la oficina,Igual que cuando iba todos los días a la oficina,Menor que cuando iba todos los días a la oficina,Igual que cuando iba todos los días a la oficina,Mayor que cuando iba todos los días a la oficina,Mucho menor que cuando iba todos los días a la oficina,Menor que cuando iba todos los días a la oficina,Mayor que cuando iba todos los días a la oficina,Mucho menor que cuando iba todos los días a la oficina,Menores que cuando iba todos los días a la oficina,Igual que cuando iba todos los días a la oficina,Mayor que cuando iba todos los días a la oficina,dxcorzo@gmail.com,301+ empleados,0
A11: 45573.488 | B11: Colombia | C11: <35 años | D11: Masculino | E11: Universitario | F11: Como empleado de una empresa | G11: EEUU | H11: 5-10 años | I11: <5 años | J11: Web Team Lead | K11: CTO | L11: Edgen AI | M11: <50 empleados | N11: Empresa que desarrolla software a medida partiendo desde cero | O11: Multinacional | P11: Muy Frecuentemente | Q11: Alto | R11: >5 días | S11: Ninguno | T11: No tienen oficinas | X11: Remota ( todos los días en casa) | Y11: Consensuada por las dos partes | Z11: En desacuerdo | AA11: Mayor que cuando iba todos los días a la oficina | AB11: Mayor que cuando iba todos los días a la oficina | AC11: Menor que cuando iba todos los días a la oficina | AD11: Diferentes que cuando iba todos los días a la oficina, ahora necesito menos horas para hacer lo mismo | AE11: Todas por videoconferencia | AF11: Menor que cuando eran en la oficina | AG11: Mucho Mayor que cuando iba todos los días a la oficina | AH11: Mucho Mayor que cuando iba todos los días a la oficina | AI11: Mucho Mayor que cuando iba todos los días a la oficina | AJ11: Mayor que cuando iba todos los días a la oficina | AK11: Igual que cuando iba todos los días a la oficina | AL11: Mejora mi desempeño en el trabajo | AM11: Mejoran mucho mi productividad | AN11: Mayor que cuando iba todos los días a la oficina | AO11: Menor que cuando iba todos los días a la oficina | AP11: Igual que cuando iba todos los días a la oficina | AQ11: Mucho más que cuando iba todos los días a la oficina | AR11: Menos que cuando iba todos los días a la oficina | AS11: Mucho menos que cuando iba todos los días a la oficina | AT11: Mucho menos que cuando iba todos los días a la oficina | AU11: Menos que cuando iba todos los días a la oficina | AV11: Menos que cuando iba todos los días a la oficina | AW11: Mas que cuando iba todos los días a la oficina | AX11: Igual que cuando iba todos los días a la oficina | AY11: Mayores que cuando iba todos los días a la oficina | AZ11: Mayor que cuando iba todos los días a la oficina | BA11: Mucho Mayor que cuando iba todos los días a la oficina | BB11: Menor que cuando iba todos los días a la oficina | BC11: Mayor que cuando iba todos los días a la oficina | BD11: Menor que cuando iba todos los días a la oficina | BE11: Mayor que cuando iba todos los días a la oficina | BF11: Igual que cuando iba todos los días a la oficina | BG11: Mucho mayor que cuando iba todos los días a la oficina | BH11: Menores que cuando iba todos los días a la oficina | BI11: Mucho mayor que cuando iba todos los días a la oficina | BJ11: Iguales que cuando iba todos los días a la oficina | BK11: Mayor que cuando iba todos los días a la oficina | BL11: Mucho mayores que cuando iba todos los días a la oficina | BM11: No tengo que utilizar diferentes idiomas en mi trabajo | BN11: Igual que cuando iba todos los días a la oficina | BO11: Menor que cuando iba todos los días a la oficina | BP11: Menores que cuando iba todos los días a la oficina | BQ11: Mayor que cuando iba todos los días a la oficina | BR11: Igual que cuando iba todos los días a la oficina | BS11: Mucho más que cuando iba todos los días a la oficina | BT11: Iguales que cuando iba todos los días a la oficina | BU11: Igual que cuando iba todos los días a la oficina | BV11: Igual que cuando iba todos los días a la oficina | BW11: Mayor que cuando iba todos los días a la oficina | BX11: Mucho mayor que cuando iba todos los días a la oficina | BY11: Mayor que cuando iba todos los días a la oficina | BZ11: Mayor que cuando iba todos los días a la oficina | CA11: Mucho Mayor que cuando iba todos los días a la oficina | CB11: Mayor que cuando iba todos los días a la oficina | CC11: Igual que cuando iba todos los días a la oficina | CD11: Menor que cuando iba todos los días a la oficina | CE11: Igual que cuando iba todos los días a la oficina | CF11: Iguales que cuando iba todos los días a la oficina | CG11: Mayor que cuando iba todos los días a la oficina | CH11: Mucho Mayor que cuando iba todos los días a la oficina | CI11: Menor que cuando iba todos los días a la oficina | CJ11: Igual que cuando iba todos los días a la oficina | CK11: Igual que cuando iba todos los días a la oficina | CL11: Igual que cuando iba todos los días a la oficina | CM11: Igual que cuando iba todos los días a la oficina | CN11: Igual que cuando iba todos los días a la oficina | CO11: Igual que cuando iba todos los días a la oficina | CP11: Igual que cuando iba todos los días a la oficina | CQ11: Mayor que cuando iba todos los días a la oficina | CR11: Igual que cuando iba todos los días a la oficina | CS11: Mayores que cuando iba todos los días a la oficina | CT11: Igual que cuando iba todos los días a la oficina | CU11: Mayor que cuando iba todos los días a la oficina | CV11: encuestauniandes@estebandalelr.co | CW11: <301 empleados | CX11: =VLOOKUP(K11,Sheet2!$A$2:$B$58,2,0) -> 1 | CY11: =_xlfn.TEXTJOIN(",",FALSE,A11:CX11) -> 45573,4878474074,Colombia,<35 años,Masculino,Universitario,Como empleado de una empresa,EEUU,5-10 años,<5 años,Web Team Lead,CTO,Edgen AI,<50 empleados,Empresa que desarrolla software a medida partiendo desde cero,Multinacional,Muy Frecuentemente,Alto,>5 días,Ninguno,No tienen oficinas,,,,Remota ( todos los días en casa),Consensuada por las dos partes,En desacuerdo,Mayor que cuando iba todos los días a la oficina,Mayor que cuando iba todos los días a la oficina,Menor que cuando iba todos los días a la oficina,Diferentes que cuando iba todos los días a la oficina, ahora necesito menos horas para hacer lo mismo,Todas por videoconferencia,Menor que cuando eran en la oficina,Mucho Mayor que cuando iba todos los días a la oficina,Mucho Mayor que cuando iba todos los días a la oficina,Mucho Mayor que cuando iba todos los días a la oficina,Mayor que cuando iba todos los días a la oficina,Igual que cuando iba todos los días a la oficina,Mejora mi desempeño en el trabajo,Mejoran mucho mi productividad,Mayor que cuando iba todos los días a la oficina,Menor que cuando iba todos los días a la oficina,Igual que cuando iba todos los días a la oficina,Mucho más que cuando iba todos los días a la oficina,Menos que cuando iba todos los días a la oficina,Mucho menos que cuando iba todos los días a la oficina,Mucho menos que cuando iba todos los días a la oficina,Menos que cuando iba todos los días a la oficina,Menos que cuando iba todos los días a la oficina,Mas que cuando iba todos los días a la oficina,Igual que cuando iba todos los días a la oficina,Mayores que cuando iba todos los días a la oficina,Mayor que cuando iba todos los días a la oficina,Mucho Mayor que cuando iba todos los días a la oficina,Menor que cuando iba todos los días a la oficina,Mayor que cuando iba todos los días a la oficina,Menor que cuando iba todos los días a la oficina,Mayor que cuando iba todos los días a la oficina,Igual que cuando iba todos los días a la oficina,Mucho mayor que cuando iba todos los días a la oficina,Menores que cuando iba todos los días a la oficina,Mucho mayor que cuando iba todos los días a la oficina,Iguales que cuando iba todos los días a la oficina,Mayor que cuando iba todos los días a la oficina,Mucho mayores que cuando iba todos los días a la oficina,No tengo que utilizar diferentes idiomas en mi trabajo,Igual que cuando iba todos los días a la oficina,Menor que cuando iba todos los días a la oficina,Menores que cuando iba todos los días a la oficina,Mayor que cuando iba todos los días a la oficina,Igual que cuando iba todos los días a la oficina,Mucho más que cuando iba todos los días a la oficina,Iguales que cuando iba todos los días a la oficina,Igual que cuando iba todos los días a la oficina,Igual que cuando iba todos los días a la oficina,Mayor que cuando iba todos los días a la oficina,Mucho mayor que cuando iba todos los días a la oficina,Mayor que cuando iba todos los días a la oficina,Mayor que cuando iba todos los días a la oficina,Mucho Mayor que cuando iba todos los días a la oficina,Mayor que cuando iba todos los días a la oficina,Igual que cuando iba todos los días a la oficina,Menor que cuando iba todos los días a la oficina,Igual que cuando iba todos los días a la oficina,Iguales que cuando iba todos los días a la oficina,Mayor que cuando iba todos los días a la oficina,Mucho Mayor que cuando iba todos los días a la oficina,Menor que cuando iba todos los días a la oficina,Igual que cuando iba todos los días a la oficina,Igual que cuando iba todos los días a la oficina,Igual que cuando iba todos los días a la oficina,Igual que cuando iba todos los días a la oficina,Igual que cuando iba todos los días a la oficina,Igual que cuando iba todos los días a la oficina,Igual que cuando iba todos los días a la oficina,Mayor que cuando iba todos los días a la oficina,Igual que cuando iba todos los días a la oficina,Mayores que cuando iba todos los días a la oficina,Igual que cuando iba todos los días a la oficina,Mayor que cuando iba todos los días a la oficina,encuestauniandes@estebandalelr.co,<301 empleados,1
A12: 45560.533 | B12: España | C12: <35 años | D12: Masculino | E12: Master | F12: Como empleado de una empresa | G12: Suiza | H12: 11-20 años | I12: 10-20 años | J12: Desarrollador, Project Manager, Agile Coach | K12: Agile Coach / Delivery Manager | L12: Sportradar | M12: >500 empleados. | N12: Empresa que desarrolla software a medida partiendo desde cero | O12: Multinacional | P12: Muy Frecuentemente | Q12: Alto | R12: >5 días | S12: Ninguno | T12: Nunca | X12: Híbrida casa (más días en casa que en la oficina) | Y12: Impuesta por la empresa | Z12: De acuerdo | AA12: Igual que cuando iba todos los días a la oficina | AB12: Igual que cuando iba todos los días a la oficina | AC12: Igual que cuando iba todos los días a la oficina | AD12: Diferentes que cuando iba todos los días a la oficina, ahora necesito menos horas para hacer lo mismo | AE12: Todas por videoconferencia | AF12: Menor que cuando eran en la oficina | AG12: Mayor que cuando iba todos los días a la oficina | AH12: Igual que cuando iba todos los días a la oficina | AI12: Igual que cuando iba todos los días a la oficina | AJ12: Mayor que cuando iba todos los días a la oficina | AK12: Mayor que cuando iba todos los días a la oficina | AL12: Mejora mi desempeño en el trabajo | AM12: Mejoran mi productividad | AN12: Igual que cuando iba todos los días a la oficina | AO12: Menor que cuando iba todos los días a la oficina | AP12: Igual que cuando iba todos los días a la oficina | AQ12: Menos que cuando iba todos los días a la oficina | AR12: Menos que cuando iba todos los días a la oficina | AS12: Mucho menos que cuando iba todos los días a la oficina | AT12: Mucho más que cuando iba todos los días a la oficina | AU12: Igual que cuando iba todos los días a la oficina | AV12: Mucho más que cuando iba todos los días a la oficina | AW12: Igual que cuando iba todos los días a la oficina | AX12: Igual que cuando iba todos los días a la oficina | AY12: Iguales que cuando iba todos los días a la oficina | AZ12: Igual que cuando iba todos los días a la oficina | BA12: Igual que cuando iba todos los días a la oficina | BB12: Menor que cuando iba todos los días a la oficina | BC12: Igual que cuando iba todos los días a la oficina | BD12: Menor que cuando iba todos los días a la oficina | BE12: Igual que cuando iba todos los días a la oficina | BF12: Igual que cuando iba todos los días a la oficina | BG12: Mucho mayor que cuando iba todos los días a la oficina | BH12: Iguales que cuando iba todos los días a la oficina | BI12: Mucho mayor que cuando iba todos los días a la oficina | BJ12: Mucho menores que cuando iba todos los días a la oficina | BK12: Menor que cuando iba todos los días a la oficina | BL12: Iguales que cuando iba todos los días a la oficina | BM12: Mucho menores que cuando iba todos los días a la oficina | BN12: Igual que cuando iba todos los días a la oficina | BO12: Igual que cuando iba todos los días a la oficina | BP12: Menores que cuando iba todos los días a la oficina | BQ12: Mayor que cuando iba todos los días a la oficina | BR12: Igual que cuando iba todos los días a la oficina | BS12: Igual que cuando iba todos los días a la oficina | BT12: Iguales que cuando iba todos los días a la oficina | BU12: Igual que cuando iba todos los días a la oficina | BV12: Mayor que cuando iba todos los días a la oficina | BW12: Mayor que cuando iba todos los días a la oficina | BX12: Mayor que cuando iba todos los días a la oficina | BY12: Igual que cuando iba todos los días a la oficina | BZ12: Igual que cuando iba todos los días a la oficina | CA12: Igual que cuando iba todos los días a la oficina | CB12: Mayor que cuando iba todos los días a la oficina | CC12: Mayor que cuando iba todos los días a la oficina | CD12: Igual que cuando iba todos los días a la oficina | CE12: Menos que cuando iba todos los días a la oficina | CF12: Menores que cuando iba todos los días a la oficina | CG12: Igual que cuando iba todos los días a la oficina | CH12: Mucho Mayor que cuando iba todos los días a la oficina | CI12: Igual que cuando iba todos los días a la oficina | CJ12: Menor que cuando iba todos los días a la oficina | CK12: Igual que cuando iba todos los días a la oficina | CL12: Mucho Mayor que cuando iba todos los días a la oficina | CM12: Igual que cuando iba todos los días a la oficina | CN12: Menor que cuando iba todos los días a la oficina | CO12: Mucho menor que cuando iba todos los días a la oficina | CP12: Igual que cuando iba todos los días a la oficina | CQ12: Igual que cuando iba todos los días a la oficina | CR12: Igual que cuando iba todos los días a la oficina | CS12: Iguales que cuando iba todos los días a la oficina | CT12: Igual que cuando iba todos los días a la oficina | CU12: Mayor que cuando iba todos los días a la oficina | CV12: joseanmp@gmail.com | CW12: 301+ empleados | CX12: =VLOOKUP(K12,Sheet2!$A$2:$B$58,2,0) -> 0 | CY12: =_xlfn.TEXTJOIN(",",FALSE,A12:CX12) -> 45560,5328337616,España,<35 años,Masculino,Master,Como empleado de una empresa,Suiza,11-20 años,10-20 años,Desarrollador, Project Manager, Agile Coach,Agile Coach / Delivery Manager,Sportradar,>500 empleados.,Empresa que desarrolla software a medida partiendo desde cero,Multinacional,Muy Frecuentemente,Alto,>5 días,Ninguno,Nunca,,,,Híbrida casa (más días en casa que en la oficina),Impuesta por la empresa,De acuerdo,Igual que cuando iba todos los días a la oficina,Igual que cuando iba todos los días a la oficina,Igual que cuando iba todos los días a la oficina,Diferentes que cuando iba todos los días a la oficina, ahora necesito menos horas para hacer lo mismo,Todas por videoconferencia,Menor que cuando eran en la oficina,Mayor que cuando iba todos los días a la oficina,Igual que cuando iba todos los días a la oficina,Igual que cuando iba todos los días a la oficina,Mayor que cuando iba todos los días a la oficina,Mayor que cuando iba todos los días a la oficina,Mejora mi desempeño en el trabajo,Mejoran mi productividad,Igual que cuando iba todos los días a la oficina,Menor que cuando iba todos los días a la oficina,Igual que cuando iba todos los días a la oficina,Menos que cuando iba todos los días a la oficina,Menos que cuando iba todos los días a la oficina,Mucho menos que cuando iba todos los días a la oficina,Mucho más que cuando iba todos los días a la oficina,Igual que cuando iba todos los días a la oficina,Mucho más que cuando iba todos los días a la oficina,Igual que cuando iba todos los días a la oficina,Igual que cuando iba todos los días a la oficina,Iguales que cuando iba todos los días a la oficina,Igual que cuando iba todos los días a la oficina,Igual que cuando iba todos los días a la oficina,Menor que cuando iba todos los días a la oficina,Igual que cuando iba todos los días a la oficina,Menor que cuando iba todos los días a la oficina,Igual que cuando iba todos los días a la oficina,Igual que cuando iba todos los días a la oficina,Mucho mayor que cuando iba todos los días a la oficina,Iguales que cuando iba todos los días a la oficina,Mucho mayor que cuando iba todos los días a la oficina,Mucho menores que cuando iba todos los días a la oficina,Menor que cuando iba todos los días a la oficina,Iguales que cuando iba todos los días a la oficina,Mucho menores que cuando iba todos los días a la oficina,Igual que cuando iba todos los días a la oficina,Igual que cuando iba todos los días a la oficina,Menores que cuando iba todos los días a la oficina,Mayor que cuando iba todos los días a la oficina,Igual que cuando iba todos los días a la oficina,Igual que cuando iba todos los días a la oficina,Iguales que cuando iba todos los días a la oficina,Igual que cuando iba todos los días a la oficina,Mayor que cuando iba todos los días a la oficina,Mayor que cuando iba todos los días a la oficina,Mayor que cuando iba todos los días a la oficina,Igual que cuando iba todos los días a la oficina,Igual que cuando iba todos los días a la oficina,Igual que cuando iba todos los días a la oficina,Mayor que cuando iba todos los días a la oficina,Mayor que cuando iba todos los días a la oficina,Igual que cuando iba todos los días a la oficina,Menos que cuando iba todos los días a la oficina,Menores que cuando iba todos los días a la oficina,Igual que cuando iba todos los días a la oficina,Mucho Mayor que cuando iba todos los días a la oficina,Igual que cuando iba todos los días a la oficina,Menor que cuando iba todos los días a la oficina,Igual que cuando iba todos los días a la oficina,Mucho Mayor que cuando iba todos los días a la oficina,Igual que cuando iba todos los días a la oficina,Menor que cuando iba todos los días a la oficina,Mucho menor que cuando iba todos los días a la oficina,Igual que cuando iba todos los días a la oficina,Igual que cuando iba todos los días a la oficina,Igual que cuando iba todos los días a la oficina,Iguales que cuando iba todos los días a la oficina,Igual que cuando iba todos los días a la oficina,Mayor que cuando iba todos los días a la oficina,joseanmp@gmail.com,301+ empleados,0
A13: 45573.688 | B13: España | C13: <35 años | D13: Masculino | E13: superiores | F13: Como empleado de una empresa | G13: España | H13: 21-30 años | I13: 20-30 años | J13: Gerente | K13: Gerente | L13: INDRA | M13: >500 empleados. | N13: Fábrica de Software | O13: Multinacional | P13: A veces | Q13: Alto | R13: >5 días | S13: Ninguno | T13: Nunca | U13: Nunca | V13: Nunca | W13: No | X13: Híbrida casa (más días en casa que en la oficina) | Y13: Consensuada por las dos partes | Z13: Totalmente en desacuerdo | AA13: Igual que cuando iba todos los días a la oficina | AB13: Igual que cuando iba todos los días a la oficina | AC13: Igual que cuando iba todos los días a la oficina | AD13: Iguales que cuando iba todos los días a la oficina | AE13: Todas por videoconferencia | AF13: Mucho menor que cuando eran en la oficina | AG13: Igual que cuando iba todos los días a la oficina | AH13: Igual que cuando iba todos los días a la oficina | AI13: Igual que cuando iba todos los días a la oficina | AJ13: Mayor que cuando iba todos los días a la oficina | AK13: Mucho Mejor que cuando iba todos los días a la oficina | AL13: Mejora mi desempeño en el trabajo | AM13: Mejoran mi productividad | AN13: Mucho mayor que cuando iba todos los días a la oficina | AO13: Mayor que cuando iba todos los días a la oficina | AP13: Menos que cuando iba todos los días a la oficina | AQ13: Igual que cuando iba todos los días a la oficina | AR13: Igual que cuando iba todos los días a la oficina | AS13: Igual que cuando iba todos los días a la oficina | AT13: Igual que cuando iba todos los días a la oficina | AU13: Igual que cuando iba todos los días a la oficina | AV13: Menos que cuando iba todos los días a la oficina | AW13: Menos que cuando iba todos los días a la oficina | AX13: Igual que cuando iba todos los días a la oficina | AY13: Iguales que cuando iba todos los días a la oficina | AZ13: Igual que cuando iba todos los días a la oficina | BA13: Igual que cuando iba todos los días a la oficina | BB13: Mayor que cuando iba todos los días a la oficina | BC13: Igual que cuando iba todos los días a la oficina | BD13: Igual que cuando iba todos los días a la oficina | BE13: Igual que cuando iba todos los días a la oficina | BF13: Mayor que cuando iba todos los días a la oficina | BG13: Mucho mayor que cuando iba todos los días a la oficina | BH13: Iguales que cuando iba todos los días a la oficina | BI13: Igual que cuando iba todos los días a la oficina | BJ13: Iguales que cuando iba todos los días a la oficina | BK13: Igual que cuando iba todos los días a la oficina | BL13: Iguales que cuando iba todos los días a la oficina | BM13: Iguales que cuando iba todos los días a la oficina | BN13: Igual que cuando iba todos los días a la oficina | BO13: Igual que cuando iba todos los días a la oficina | BP13: Menores que cuando iba todos los días a la oficina | BQ13: Mayor que cuando iba todos los días a la oficina | BR13: Igual que cuando iba todos los días a la oficina | BS13: Igual que cuando iba todos los días a la oficina | BT13: Iguales que cuando iba todos los días a la oficina | BU13: Igual que cuando iba todos los días a la oficina | BV13: Igual que cuando iba todos los días a la oficina | BW13: Mayor que cuando iba todos los días a la oficina | BX13: Mucho mayor que cuando iba todos los días a la oficina | BY13: Igual que cuando iba todos los días a la oficina | BZ13: Igual que cuando iba todos los días a la oficina | CA13: Igual que cuando iba todos los días a la oficina | CB13: Igual que cuando iba todos los días a la oficina | CC13: Igual que cuando iba todos los días a la oficina | CD13: Igual que cuando iba todos los días a la oficina | CE13: Igual que cuando iba todos los días a la oficina | CF13: Iguales que cuando iba todos los días a la oficina | CG13: Igual que cuando iba todos los días a la oficina | CH13: Menor que cuando iba todos los días a la oficina | CI13: Igual que cuando iba todos los días a la oficina | CJ13: Menor que cuando iba todos los días a la oficina | CK13: Igual que cuando iba todos los días a la oficina | CL13: Igual que cuando iba todos los días a la oficina | CM13: Igual que cuando iba todos los días a la oficina | CN13: Igual que cuando iba todos los días a la oficina | CO13: Menor que cuando iba todos los días a la oficina | CP13: Igual que cuando iba todos los días a la oficina | CQ13: Igual que cuando iba todos los días a la oficina | CR13: Menor que cuando iba todos los días a la oficina | CS13: Iguales que cuando iba todos los días a la oficina | CT13: Igual que cuando iba todos los días a la oficina | CU13: Igual que cuando iba todos los días a la oficina | CW13: 301+ empleados | CX13: =VLOOKUP(K13,Sheet2!$A$2:$B$58,2,0) -> 0 | CY13: =_xlfn.TEXTJOIN(",",FALSE,A13:CX13) -> 45573,6883462847,España,<35 años,Masculino,superiores,Como empleado de una empresa,España,21-30 años,20-30 años,Gerente,Gerente,INDRA,>500 empleados.,Fábrica de Software,Multinacional,A veces,Alto,>5 días,Ninguno,Nunca,Nunca,Nunca,No,Híbrida casa (más días en casa que en la oficina),Consensuada por las dos partes,Totalmente en desacuerdo,Igual que cuando iba todos los días a la oficina,Igual que cuando iba todos los días a la oficina,Igual que cuando iba todos los días a la oficina,Iguales que cuando iba todos los días a la oficina,Todas por videoconferencia,Mucho menor que cuando eran en la oficina,Igual que cuando iba todos los días a la oficina,Igual que cuando iba todos los días a la oficina,Igual que cuando iba todos los días a la oficina,Mayor que cuando iba todos los días a la oficina,Mucho Mejor que cuando iba todos los días a la oficina,Mejora mi desempeño en el trabajo,Mejoran mi productividad,Mucho mayor que cuando iba todos los días a la oficina,Mayor que cuando iba todos los días a la oficina,Menos que cuando iba todos los días a la oficina,Igual que cuando iba todos los días a la oficina,Igual que cuando iba todos los días a la oficina,Igual que cuando iba todos los días a la oficina,Igual que cuando iba todos los días a la oficina,Igual que cuando iba todos los días a la oficina,Menos que cuando iba todos los días a la oficina,Menos que cuando iba todos los días a la oficina,Igual que cuando iba todos los días a la oficina,Iguales que cuando iba todos los días a la oficina,Igual que cuando iba todos los días a la oficina,Igual que cuando iba todos los días a la oficina,Mayor que cuando iba todos los días a la oficina,Igual que cuando iba todos los días a la oficina,Igual que cuando iba todos los días a la oficina,Igual que cuando iba todos los días a la oficina,Mayor que cuando iba todos los días a la oficina,Mucho mayor que cuando iba todos los días a la oficina,Iguales que cuando iba todos los días a la oficina,Igual que cuando iba todos los días a la oficina,Iguales que cuando iba todos los días a la oficina,Igual que cuando iba todos los días a la oficina,Iguales que cuando iba todos los días a la oficina,Iguales que cuando iba todos los días a la oficina,Igual que cuando iba todos los días a la oficina,Igual que cuando iba todos los días a la oficina,Menores que cuando iba todos los días a la oficina,Mayor que cuando iba todos los días a la oficina,Igual que cuando iba todos los días a la oficina,Igual que cuando iba todos los días a la oficina,Iguales que cuando iba todos los días a la oficina,Igual que cuando iba todos los días a la oficina,Igual que cuando iba todos los días a la oficina,Mayor que cuando iba todos los días a la oficina,Mucho mayor que cuando iba todos los días a la oficina,Igual que cuando iba todos los días a la oficina,Igual que cuando iba todos los días a la oficina,Igual que cuando iba todos los días a la oficina,Igual que cuando iba todos los días a la oficina,Igual que cuando iba todos los días a la oficina,Igual que cuando iba todos los días a la oficina,Igual que cuando iba todos los días a la oficina,Iguales que cuando iba todos los días a la oficina,Igual que cuando iba todos los días a la oficina,Menor que cuando iba todos los días a la oficina,Igual que cuando iba todos los días a la oficina,Menor que cuando iba todos los días a la oficina,Igual que cuando iba todos los días a la oficina,Igual que cuando iba todos los días a la oficina,Igual que cuando iba todos los días a la oficina,Igual que cuando iba todos los días a la oficina,Menor que cuando iba todos los días a la oficina,Igual que cuando iba todos los días a la oficina,Igual que cuando iba todos los días a la oficina,Menor que cuando iba todos los días a la oficina,Iguales que cuando iba todos los días a la oficina,Igual que cuando iba todos los días a la oficina,Igual que cuando iba todos los días a la oficina,,301+ empleados,0
A14: 45572.493 | B14: España | C14: <35 años | D14: Masculino | E14: Ingenieria en informatica | F14: Como empleado de una empresa | G14: Japón | H14: 11-20 años | I14: 10-20 años | J14: Lider tecnico | K14: Project Manager | L14: NTT Data | M14: >500 empleados. | N14: Empresa que desarrolla software a medida partiendo desde cero | O14: Multinacional | P14: A veces | Q14: Alto | R14: >5 días | S14: 1-2 días | T14: Temas importantes puntuales | U14: lo planifico cuando yo puedo | V14: cuando concilie uno mejor | W14: cafe gratis y desayunos | X14: Híbrida casa (más días en casa que en la oficina) | Y14: Decidida por ti | Z14: En desacuerdo | AA14: Igual que cuando iba todos los días a la oficina | AB14: Igual que cuando iba todos los días a la oficina | AC14: Igual que cuando iba todos los días a la oficina | AD14: Iguales que cuando iba todos los días a la oficina | AE14: Casi todas por videoconferencia | AF14: Igual que cuando eran en la oficina | AG14: Mayor que cuando iba todos los días a la oficina | AH14: Mucho Mayor que cuando iba todos los días a la oficina | AI14: Mucho Mayor que cuando iba todos los días a la oficina | AJ14: Mayor que cuando iba todos los días a la oficina | AK14: Mayor que cuando iba todos los días a la oficina | AL14: Mejora mi desempeño en el trabajo | AM14: Mejoran mi productividad | AN14: Mayor que cuando iba todos los días a la oficina | AO14: Mucho mayor que cuando iba todos los días a la oficina | AP14: Mucho más que cuando iba todos los días a la oficina | AQ14: Más que cuando iba todos los días a la oficina | AR14: Más que cuando iba todos los días a la oficina | AS14: Más que cuando iba todos los días a la oficina | AT14: Mucho más que cuando iba todos los días a la oficina | AU14: Mas que cuando iba todos los días a la oficina | AV14: Mucho más que cuando iba todos los días a la oficina | AW14: Mas que cuando iba todos los días a la oficina | AX14: Mas que cuando iba todos los días a la oficina | AY14: Mayores que cuando iba todos los días a la oficina | AZ14: Mayor que cuando iba todos los días a la oficina | BA14: Mayor que cuando iba todos los días a la oficina | BB14: Igual que cuando iba todos los días a la oficina | BC14: Igual que cuando iba todos los días a la oficina | BD14: Igual que cuando iba todos los días a la oficina | BE14: Igual que cuando iba todos los días a la oficina | BF14: Igual que cuando iba todos los días a la oficina | BG14: Igual que cuando iba todos los días a la oficina | BH14: Iguales que cuando iba todos los días a la oficina | BI14: Igual que cuando iba todos los días a la oficina | BJ14: Iguales que cuando iba todos los días a la oficina | BK14: Igual que cuando iba todos los días a la oficina | BL14: Iguales que cuando iba todos los días a la oficina | BM14: Iguales que cuando iba todos los días a la oficina | BN14: Igual que cuando iba todos los días a la oficina | BO14: Igual que cuando iba todos los días a la oficina | BP14: Iguales que cuando iba todos los días a la oficina | BQ14: Igual que cuando iba todos los días a la oficina | BR14: Igual que cuando iba todos los días a la oficina | BS14: Igual que cuando iba todos los días a la oficina | BT14: Iguales que cuando iba todos los días a la oficina | BU14: Igual que cuando iba todos los días a la oficina | BV14: Igual que cuando iba todos los días a la oficina | BW14: Igual que cuando iba todos los días a la oficina | BX14: Igual que cuando iba todos los días a la oficina | BY14: Igual que cuando iba todos los días a la oficina | BZ14: Igual que cuando iba todos los días a la oficina | CA14: Igual que cuando iba todos los días a la oficina | CB14: Igual que cuando iba todos los días a la oficina | CC14: Igual que cuando iba todos los días a la oficina | CD14: Igual que cuando iba todos los días a la oficina | CE14: Igual que cuando iba todos los días a la oficina | CF14: Iguales que cuando iba todos los días a la oficina | CG14: Igual que cuando iba todos los días a la oficina | CH14: Igual que cuando iba todos los días a la oficina | CI14: Igual que cuando iba todos los días a la oficina | CJ14: Igual que cuando iba todos los días a la oficina | CK14: Igual que cuando iba todos los días a la oficina | CL14: Igual que cuando iba todos los días a la oficina | CM14: Igual que cuando iba todos los días a la oficina | CN14: Igual que cuando iba todos los días a la oficina | CO14: Igual que cuando iba todos los días a la oficina | CP14: Igual que cuando iba todos los días a la oficina | CQ14: Igual que cuando iba todos los días a la oficina | CR14: Igual que cuando iba todos los días a la oficina | CS14: Iguales que cuando iba todos los días a la oficina | CT14: Igual que cuando iba todos los días a la oficina | CU14: Igual que cuando iba todos los días a la oficina | CW14: 301+ empleados | CX14: =VLOOKUP(K14,Sheet2!$A$2:$B$58,2,0) -> 0 | CY14: =_xlfn.TEXTJOIN(",",FALSE,A14:CX14) -> 45572,4933562616,España,<35 años,Masculino,Ingenieria en informatica,Como empleado de una empresa,Japón,11-20 años,10-20 años,Lider tecnico,Project Manager,NTT Data,>500 empleados.,Empresa que desarrolla software a medida partiendo desde cero,Multinacional,A veces,Alto,>5 días,1-2 días,Temas importantes puntuales,lo planifico cuando yo puedo,cuando concilie uno mejor,cafe gratis y desayunos,Híbrida casa (más días en casa que en la oficina),Decidida por ti,En desacuerdo,Igual que cuando iba todos los días a la oficina,Igual que cuando iba todos los días a la oficina,Igual que cuando iba todos los días a la oficina,Iguales que cuando iba todos los días a la oficina,Casi todas por videoconferencia,Igual que cuando eran en la oficina,Mayor que cuando iba todos los días a la oficina,Mucho Mayor que cuando iba todos los días a la oficina,Mucho Mayor que cuando iba todos los días a la oficina,Mayor que cuando iba todos los días a la oficina,Mayor que cuando iba todos los días a la oficina,Mejora mi desempeño en el trabajo,Mejoran mi productividad,Mayor que cuando iba todos los días a la oficina,Mucho mayor que cuando iba todos los días a la oficina,Mucho más que cuando iba todos los días a la oficina,Más que cuando iba todos los días a la oficina,Más que cuando iba todos los días a la oficina,Más que cuando iba todos los días a la oficina,Mucho más que cuando iba todos los días a la oficina,Mas que cuando iba todos los días a la oficina,Mucho más que cuando iba todos los días a la oficina,Mas que cuando iba todos los días a la oficina,Mas que cuando iba todos los días a la oficina,Mayores que cuando iba todos los días a la oficina,Mayor que cuando iba todos los días a la oficina,Mayor que cuando iba todos los días a la oficina,Igual que cuando iba todos los días a la oficina,Igual que cuando iba todos los días a la oficina,Igual que cuando iba todos los días a la oficina,Igual que cuando iba todos los días a la oficina,Igual que cuando iba todos los días a la oficina,Igual que cuando iba todos los días a la oficina,Iguales que cuando iba todos los días a la oficina,Igual que cuando iba todos los días a la oficina,Iguales que cuando iba todos los días a la oficina,Igual que cuando iba todos los días a la oficina,Iguales que cuando iba todos los días a la oficina,Iguales que cuando iba todos los días a la oficina,Igual que cuando iba todos los días a la oficina,Igual que cuando iba todos los días a la oficina,Iguales que cuando iba todos los días a la oficina,Igual que cuando iba todos los días a la oficina,Igual que cuando iba todos los días a la oficina,Igual que cuando iba todos los días a la oficina,Iguales que cuando iba todos los días a la oficina,Igual que cuando iba todos los días a la oficina,Igual que cuando iba todos los días a la oficina,Igual que cuando iba todos los días a la oficina,Igual que cuando iba todos los días a la oficina,Igual que cuando iba todos los días a la oficina,Igual que cuando iba todos los días a la oficina,Igual que cuando iba todos los días a la oficina,Igual que cuando iba todos los días a la oficina,Igual que cuando iba todos los días a la oficina,Igual que cuando iba todos los días a la oficina,Igual que cuando iba todos los días a la oficina,Iguales que cuando iba todos los días a la oficina,Igual que cuando iba todos los días a la oficina,Igual que cuando iba todos los días a la oficina,Igual que cuando iba todos los días a la oficina,Igual que cuando iba todos los días a la oficina,Igual que cuando iba todos los días a la oficina,Igual que cuando iba todos los días a la oficina,Igual que cuando iba todos los días a la oficina,Igual que cuando iba todos los días a la oficina,Igual que cuando iba todos los días a la oficina,Igual que cuando iba todos los días a la oficina,Igual que cuando iba todos los días a la oficina,Igual que cuando iba todos los días a la oficina,Iguales que cuando iba todos los días a la oficina,Igual que cuando iba todos los días a la oficina,Igual que cuando iba todos los días a la oficina,,301+ empleados,0
A15: 45560.534 | B15: España | C15: <35 años | D15: Masculino | E15: Universitarios | F15: Como empleado de una empresa | G15: España | H15: 11-20 años | I15: 5-10 años | J15: Senior Project Manager | K15: Head of Engineering | L15: NETEX Learning | M15: 151-300 empleados | N15: Fábrica de Software | O15: Multinacional | P15: Frecuentemente | Q15: Alto | R15: >5 días | S15: Ninguno | T15: Voy una vez al mes a la reunión mensual de alineamiento | U15: -- | V15: -- | W15: Corre con todos los gastos de desplazamiento y dietas | X15: Híbrida casa (más días en casa que en la oficina) | Y15: Consensuada por las dos partes | Z15: En desacuerdo | AA15: Igual que cuando iba todos los días a la oficina | AB15: Igual que cuando iba todos los días a la oficina | AC15: Igual que cuando iba todos los días a la oficina | AD15: Diferentes que cuando iba todos los días a la oficina, ahora necesito menos horas para hacer lo mismo | AE15: Casi todas por videoconferencia | AF15: Igual que cuando eran en la oficina | AG15: Mayor que cuando iba todos los días a la oficina | AH15: Mayor que cuando iba todos los días a la oficina | AI15: Mayor que cuando iba todos los días a la oficina | AJ15: Mayor que cuando iba todos los días a la oficina | AK15: Mucho Mejor que cuando iba todos los días a la oficina | AL15: No me influye | AM15: No afectan a mi productividad | AN15: Igual que cuando iba todos los días a la oficina | AO15: Igual que cuando iba todos los días a la oficina | AP15: Igual que cuando iba todos los días a la oficina | AQ15: Igual que cuando iba todos los días a la oficina | AR15: Igual que cuando iba todos los días a la oficina | AS15: Igual que cuando iba todos los días a la oficina | AT15: Igual que cuando iba todos los días a la oficina | AU15: Igual que cuando iba todos los días a la oficina | AV15: Igual que cuando iba todos los días a la oficina | AW15: Igual que cuando iba todos los días a la oficina | AX15: Igual que cuando iba todos los días a la oficina | AY15: Iguales que cuando iba todos los días a la oficina | AZ15: Igual que cuando iba todos los días a la oficina | BA15: Igual que cuando iba todos los días a la oficina | BB15: Menor que cuando iba todos los días a la oficina | BC15: Igual que cuando iba todos los días a la oficina | BD15: Igual que cuando iba todos los días a la oficina | BE15: Igual que cuando iba todos los días a la oficina | BF15: Igual que cuando iba todos los días a la oficina | BG15: Mucho mayor que cuando iba todos los días a la oficina | BH15: Iguales que cuando iba todos los días a la oficina | BI15: Mayor que cuando iba todos los días a la oficina | BJ15: Iguales que cuando iba todos los días a la oficina | BK15: Igual que cuando iba todos los días a la oficina | BL15: Iguales que cuando iba todos los días a la oficina | BM15: Iguales que cuando iba todos los días a la oficina | BN15: Igual que cuando iba todos los días a la oficina | BO15: Mayor que cuando iba todos los días a la oficina | BP15: Menores que cuando iba todos los días a la oficina | BQ15: Mayor que cuando iba todos los días a la oficina | BR15: Igual que cuando iba todos los días a la oficina | BS15: Igual que cuando iba todos los días a la oficina | BT15: Iguales que cuando iba todos los días a la oficina | BU15: Igual que cuando iba todos los días a la oficina | BV15: Mayor que cuando iba todos los días a la oficina | BW15: Mayor que cuando iba todos los días a la oficina | BX15: Mucho mayor que cuando iba todos los días a la oficina | BY15: Igual que cuando iba todos los días a la oficina | BZ15: Igual que cuando iba todos los días a la oficina | CA15: Igual que cuando iba todos los días a la oficina | CB15: Mayor que cuando iba todos los días a la oficina | CC15: Igual que cuando iba todos los días a la oficina | CD15: Igual que cuando iba todos los días a la oficina | CE15: Igual que cuando iba todos los días a la oficina | CF15: Iguales que cuando iba todos los días a la oficina | CG15: Igual que cuando iba todos los días a la oficina | CH15: Mucho Mayor que cuando iba todos los días a la oficina | CI15: Mayor que cuando iba todos los días a la oficina | CJ15: Igual que cuando iba todos los días a la oficina | CK15: Igual que cuando iba todos los días a la oficina | CL15: Igual que cuando iba todos los días a la oficina | CM15: Igual que cuando iba todos los días a la oficina | CN15: Igual que cuando iba todos los días a la oficina | CO15: Menor que cuando iba todos los días a la oficina | CP15: Igual que cuando iba todos los días a la oficina | CQ15: Igual que cuando iba todos los días a la oficina | CR15: Igual que cuando iba todos los días a la oficina | CS15: Iguales que cuando iba todos los días a la oficina | CT15: Igual que cuando iba todos los días a la oficina | CU15: Igual que cuando iba todos los días a la oficina | CW15: <301 empleados | CX15: =VLOOKUP(K15,Sheet2!$A$2:$B$58,2,0) -> 0 | CY15: =_xlfn.TEXTJOIN(",",FALSE,A15:CX15) -> 45560,5338653241,España,<35 años,Masculino,Universitarios,Como empleado de una empresa,España,11-20 años,5-10 años,Senior Project Manager,Head of Engineering,NETEX Learning,151-300 empleados,Fábrica de Software,Multinacional,Frecuentemente,Alto,>5 días,Ninguno,Voy una vez al mes a la reunión mensual de alineamiento,--,--,Corre con todos los gastos de desplazamiento y dietas,Híbrida casa (más días en casa que en la oficina),Consensuada por las dos partes,En desacuerdo,Igual que cuando iba todos los días a la oficina,Igual que cuando iba todos los días a la oficina,Igual que cuando iba todos los días a la oficina,Diferentes que cuando iba todos los días a la oficina, ahora necesito menos horas para hacer lo mismo,Casi todas por videoconferencia,Igual que cuando eran en la oficina,Mayor que cuando iba todos los días a la oficina,Mayor que cuando iba todos los días a la oficina,Mayor que cuando iba todos los días a la oficina,Mayor que cuando iba todos los días a la oficina,Mucho Mejor que cuando iba todos los días a la oficina,No me influye,No afectan a mi productividad,Igual que cuando iba todos los días a la oficina,Igual que cuando iba todos los días a la oficina,Igual que cuando iba todos los días a la oficina,Igual que cuando iba todos los días a la oficina,Igual que cuando iba todos los días a la oficina,Igual que cuando iba todos los días a la oficina,Igual que cuando iba todos los días a la oficina,Igual que cuando iba todos los días a la oficina,Igual que cuando iba todos los días a la oficina,Igual que cuando iba todos los días a la oficina,Igual que cuando iba todos los días a la oficina,Iguales que cuando iba todos los días a la oficina,Igual que cuando iba todos los días a la oficina,Igual que cuando iba todos los días a la oficina,Menor que cuando iba todos los días a la oficina,Igual que cuando iba todos los días a la oficina,Igual que cuando iba todos los días a la oficina,Igual que cuando iba todos los días a la oficina,Igual que cuando iba todos los días a la oficina,Mucho mayor que cuando iba todos los días a la oficina,Iguales que cuando iba todos los días a la oficina,Mayor que cuando iba todos los días a la oficina,Iguales que cuando iba todos los días a la oficina,Igual que cuando iba todos los días a la oficina,Iguales que cuando iba todos los días a la oficina,Iguales que cuando iba todos los días a la oficina,Igual que cuando iba todos los días a la oficina,Mayor que cuando iba todos los días a la oficina,Menores que cuando iba todos los días a la oficina,Mayor que cuando iba todos los días a la oficina,Igual que cuando iba todos los días a la oficina,Igual que cuando iba todos los días a la oficina,Iguales que cuando iba todos los días a la oficina,Igual que cuando iba todos los días a la oficina,Mayor que cuando iba todos los días a la oficina,Mayor que cuando iba todos los días a la oficina,Mucho mayor que cuando iba todos los días a la oficina,Igual que cuando iba todos los días a la oficina,Igual que cuando iba todos los días a la oficina,Igual que cuando iba todos los días a la oficina,Mayor que cuando iba todos los días a la oficina,Igual que cuando iba todos los días a la oficina,Igual que cuando iba todos los días a la oficina,Igual que cuando iba todos los días a la oficina,Iguales que cuando iba todos los días a la oficina,Igual que cuando iba todos los días a la oficina,Mucho Mayor que cuando iba todos los días a la oficina,Mayor que cuando iba todos los días a la oficina,Igual que cuando iba todos los días a la oficina,Igual que cuando iba todos los días a la oficina,Igual que cuando iba todos los días a la oficina,Igual que cuando iba todos los días a la oficina,Igual que cuando iba todos los días a la oficina,Menor que cuando iba todos los días a la oficina,Igual que cuando iba todos los días a la oficina,Igual que cuando iba todos los días a la oficina,Igual que cuando iba todos los días a la oficina,Iguales que cuando iba todos los días a la oficina,Igual que cuando iba todos los días a la oficina,Igual que cuando iba todos los días a la oficina,,<301 empleados,0
A16: 45577.375 | B16: España | C16: <35 años | D16: Masculino | E16: Magister | F16: Como empleado de una empresa | G16: España | H16: 11-20 años | I16: 5-10 años | J16: Gerente de Desarrollo | K16: Tech Lead | L16: Celering Smart Mobility Services | M16: <50 empleados | N16: Empresa que desarrolla software a medida partiendo desde cero | O16: Local | P16: Muy Frecuentemente | Q16: Alto | R16: >5 días | S16: Ninguno | T16: Reuniones puntuales, ejemplo: comité de dirección. | X16: Remota ( todos los días en casa) | Y16: Consensuada por las dos partes | Z16: En desacuerdo | AA16: Igual que cuando iba todos los días a la oficina | AB16: Menor que cuando iba todos los días a la oficina | AC16: Igual que cuando iba todos los días a la oficina | AD16: Diferentes que cuando iba todos los días a la oficina, ahora necesito menos horas para hacer lo mismo | AE16: Casi todas por videoconferencia | AF16: Menor que cuando eran en la oficina | AG16: Mayor que cuando iba todos los días a la oficina | AH16: Mayor que cuando iba todos los días a la oficina | AI16: Mayor que cuando iba todos los días a la oficina | AJ16: Mayor que cuando iba todos los días a la oficina | AK16: Igual que cuando iba todos los días a la oficina | AL16: Mejora mi desempeño en el trabajo | AM16: No afectan a mi productividad | AN16: Igual que cuando iba todos los días a la oficina | AO16: Igual que cuando iba todos los días a la oficina | AP16: Igual que cuando iba todos los días a la oficina | AQ16: Igual que cuando iba todos los días a la oficina | AR16: No trabajo con personas con un horario distinto al mío | AS16: Igual que cuando iba todos los días a la oficina | AT16: Igual que cuando iba todos los días a la oficina | AU16: Igual que cuando iba todos los días a la oficina | AV16: Igual que cuando iba todos los días a la oficina | AW16: Igual que cuando iba todos los días a la oficina | AX16: Igual que cuando iba todos los días a la oficina | AY16: Iguales que cuando iba todos los días a la oficina | AZ16: Igual que cuando iba todos los días a la oficina | BA16: Igual que cuando iba todos los días a la oficina | BB16: Igual que cuando iba todos los días a la oficina | BC16: Igual que cuando iba todos los días a la oficina | BD16: Igual que cuando iba todos los días a la oficina | BE16: Igual que cuando iba todos los días a la oficina | BF16: Igual que cuando iba todos los días a la oficina | BG16: Mucho mayor que cuando iba todos los días a la oficina | BH16: Iguales que cuando iba todos los días a la oficina | BI16: Mayor que cuando iba todos los días a la oficina | BJ16: Iguales que cuando iba todos los días a la oficina | BK16: Igual que cuando iba todos los días a la oficina | BL16: Iguales que cuando iba todos los días a la oficina | BM16: No tengo que utilizar diferentes idiomas en mi trabajo | BN16: No trabajo con personas con distintos horarios | BO16: Igual que cuando iba todos los días a la oficina | BP16: Menores que cuando iba todos los días a la oficina | BQ16: Igual que cuando iba todos los días a la oficina | BR16: Igual que cuando iba todos los días a la oficina | BS16: Igual que cuando iba todos los días a la oficina | BT16: Iguales que cuando iba todos los días a la oficina | BU16: Igual que cuando iba todos los días a la oficina | BV16: Igual que cuando iba todos los días a la oficina | BW16: Mayor que cuando iba todos los días a la oficina | BX16: Mayor que cuando iba todos los días a la oficina | BY16: Igual que cuando iba todos los días a la oficina | BZ16: Igual que cuando iba todos los días a la oficina | CA16: Igual que cuando iba todos los días a la oficina | CB16: Menor que cuando iba todos los días a la oficina | CC16: Igual que cuando iba todos los días a la oficina | CD16: Igual que cuando iba todos los días a la oficina | CE16: Igual que cuando iba todos los días a la oficina | CF16: Iguales que cuando iba todos los días a la oficina | CG16: Igual que cuando iba todos los días a la oficina | CH16: Mucho Mayor que cuando iba todos los días a la oficina | CI16: Igual que cuando iba todos los días a la oficina | CJ16: Igual que cuando iba todos los días a la oficina | CK16: Igual que cuando iba todos los días a la oficina | CL16: Igual que cuando iba todos los días a la oficina | CM16: Igual que cuando iba todos los días a la oficina | CN16: Igual que cuando iba todos los días a la oficina | CO16: Menor que cuando iba todos los días a la oficina | CP16: Igual que cuando iba todos los días a la oficina | CQ16: Mayor que cuando iba todos los días a la oficina | CR16: Igual que cuando iba todos los días a la oficina | CS16: Iguales que cuando iba todos los días a la oficina | CT16: Igual que cuando iba todos los días a la oficina | CU16: Igual que cuando iba todos los días a la oficina | CV16: Farruza@gmail.com | CW16: <301 empleados | CX16: =VLOOKUP(K16,Sheet2!$A$2:$B$58,2,0) -> 0 | CY16: =_xlfn.TEXTJOIN(",",FALSE,A16:CX16) -> 45577,3745158333,España,<35 años,Masculino,Magister,Como empleado de una empresa,España ,11-20 años,5-10 años,Gerente de Desarrollo ,Tech Lead,Celering Smart Mobility Services ,<50 empleados,Empresa que desarrolla software a medida partiendo desde cero,Local,Muy Frecuentemente,Alto,>5 días,Ninguno,Reuniones puntuales, ejemplo: comité de dirección.,,,,Remota ( todos los días en casa),Consensuada por las dos partes,En desacuerdo,Igual que cuando iba todos los días a la oficina,Menor que cuando iba todos los días a la oficina,Igual que cuando iba todos los días a la oficina,Diferentes que cuando iba todos los días a la oficina, ahora necesito menos horas para hacer lo mismo,Casi todas por videoconferencia,Menor que cuando eran en la oficina,Mayor que cuando iba todos los días a la oficina,Mayor que cuando iba todos los días a la oficina,Mayor que cuando iba todos los días a la oficina,Mayor que cuando iba todos los días a la oficina,Igual que cuando iba todos los días a la oficina,Mejora mi desempeño en el trabajo,No afectan a mi productividad,Igual que cuando iba todos los días a la oficina,Igual que cuando iba todos los días a la oficina,Igual que cuando iba todos los días a la oficina,Igual que cuando iba todos los días a la oficina,No trabajo con personas con un horario distinto al mío,Igual que cuando iba todos los días a la oficina,Igual que cuando iba todos los días a la oficina,Igual que cuando iba todos los días a la oficina,Igual que cuando iba todos los días a la oficina,Igual que cuando iba todos los días a la oficina,Igual que cuando iba todos los días a la oficina,Iguales que cuando iba todos los días a la oficina,Igual que cuando iba todos los días a la oficina,Igual que cuando iba todos los días a la oficina,Igual que cuando iba todos los días a la oficina,Igual que cuando iba todos los días a la oficina,Igual que cuando iba todos los días a la oficina,Igual que cuando iba todos los días a la oficina,Igual que cuando iba todos los días a la oficina,Mucho mayor que cuando iba todos los días a la oficina,Iguales que cuando iba todos los días a la oficina,Mayor que cuando iba todos los días a la oficina,Iguales que cuando iba todos los días a la oficina,Igual que cuando iba todos los días a la oficina,Iguales que cuando iba todos los días a la oficina,No tengo que utilizar diferentes idiomas en mi trabajo,No trabajo con personas con distintos horarios,Igual que cuando iba todos los días a la oficina,Menores que cuando iba todos los días a la oficina,Igual que cuando iba todos los días a la oficina,Igual que cuando iba todos los días a la oficina,Igual que cuando iba todos los días a la oficina,Iguales que cuando iba todos los días a la oficina,Igual que cuando iba todos los días a la oficina,Igual que cuando iba todos los días a la oficina,Mayor que cuando iba todos los días a la oficina,Mayor que cuando iba todos los días a la oficina,Igual que cuando iba todos los días a la oficina,Igual que cuando iba todos los días a la oficina,Igual que cuando iba todos los días a la oficina,Menor que cuando iba todos los días a la oficina,Igual que cuando iba todos los días a la oficina,Igual que cuando iba todos los días a la oficina,Igual que cuando iba todos los días a la oficina,Iguales que cuando iba todos los días a la oficina,Igual que cuando iba todos los días a la oficina,Mucho Mayor que cuando iba todos los días a la oficina,Igual que cuando iba todos los días a la oficina,Igual que cuando iba todos los días a la oficina,Igual que cuando iba todos los días a la oficina,Igual que cuando iba todos los días a la oficina,Igual que cuando iba todos los días a la oficina,Igual que cuando iba todos los días a la oficina,Menor que cuando iba todos los días a la oficina,Igual que cuando iba todos los días a la oficina,Mayor que cuando iba todos los días a la oficina,Igual que cuando iba todos los días a la oficina,Iguales que cuando iba todos los días a la oficina,Igual que cuando iba todos los días a la oficina,Igual que cuando iba todos los días a la oficina,Farruza@gmail.com,<301 empleados,0
A17: 45564.064 | B17: México | C17: <35 años | D17: Masculino | E17: Universidad | F17: Como empleado de una empresa | G17: Estados Unidos | H17: 11-20 años | I17: 5-10 años | J17: Analista de Transformación | K17: Gerente | L17: Conduent | M17: >500 empleados. | N17: Empresa que subcontrata (outsourcing) los servicios de otra empresa situada en otro país | O17: Multinacional | P17: Muy Frecuentemente | Q17: Alto | R17: >5 días | S17: Ninguno | T17: Cuando es necesario y no existe otra opción | U17: Para renovar algún dato, recoger equipo o visita del cliente | V17: Cuando una persona en específico lo requiere | W17: Ninguna | X17: Remota ( todos los días en casa) | Y17: Consensuada por las dos partes | Z17: Totalmente en desacuerdo | AA17: Igual que cuando iba todos los días a la oficina | AB17: Mayor que cuando iba todos los días a la oficina | AC17: Igual que cuando iba todos los días a la oficina | AD17: Diferentes que cuando iba todos los días a la oficina, ahora necesito menos horas para hacer lo mismo | AE17: Todas por videoconferencia | AF17: Igual que cuando eran en la oficina | AG17: Mucho Mayor que cuando iba todos los días a la oficina | AH17: Mucho Mayor que cuando iba todos los días a la oficina | AI17: Mayor que cuando iba todos los días a la oficina | AJ17: Mucho Mayor que cuando iba todos los días a la oficina | AK17: Mucho Mejor que cuando iba todos los días a la oficina | AL17: Mejora mi desempeño en el trabajo | AM17: Mejoran mi productividad | AN17: Mucho mayor que cuando iba todos los días a la oficina | AO17: Menor que cuando iba todos los días a la oficina | AP17: Igual que cuando iba todos los días a la oficina | AQ17: Igual que cuando iba todos los días a la oficina | AR17: Igual que cuando iba todos los días a la oficina | AS17: Igual que cuando iba todos los días a la oficina | AT17: Igual que cuando iba todos los días a la oficina | AU17: Mucho menos que cuando iba todos los días a la oficina | AV17: Igual que cuando iba todos los días a la oficina | AW17: Mucho menos que cuando iba todos los días a la oficina | AX17: Igual que cuando iba todos los días a la oficina | AY17: Iguales que cuando iba todos los días a la oficina | AZ17: Igual que cuando iba todos los días a la oficina | BA17: Igual que cuando iba todos los días a la oficina | BB17: Mayor que cuando iba todos los días a la oficina | BC17: Mucho Mayor que cuando iba todos los días a la oficina | BD17: Igual que cuando iba todos los días a la oficina | BE17: Igual que cuando iba todos los días a la oficina | BF17: Mayor que cuando iba todos los días a la oficina | BG17: Mayor que cuando iba todos los días a la oficina | BH17: Mucho menores que cuando iba todos los días a la oficina | BI17: Mayor que cuando iba todos los días a la oficina | BJ17: Iguales que cuando iba todos los días a la oficina | BK17: Igual que cuando iba todos los días a la oficina | BL17: Iguales que cuando iba todos los días a la oficina | BM17: Iguales que cuando iba todos los días a la oficina | BN17: Igual que cuando iba todos los días a la oficina | BO17: Igual que cuando iba todos los días a la oficina | BP17: Menores que cuando iba todos los días a la oficina | BQ17: Mayor que cuando iba todos los días a la oficina | BR17: Igual que cuando iba todos los días a la oficina | BS17: Igual que cuando iba todos los días a la oficina | BT17: Iguales que cuando iba todos los días a la oficina | BU17: Igual que cuando iba todos los días a la oficina | BV17: Igual que cuando iba todos los días a la oficina | BW17: Mucho Mayor que cuando iba todos los días a la oficina | BX17: Mucho mayor que cuando iba todos los días a la oficina | BY17: Mucho Mayor que cuando iba todos los días a la oficina | BZ17: Mucho Mayor que cuando iba todos los días a la oficina | CA17: Mucho Mayor que cuando iba todos los días a la oficina | CB17: Mucho Mayor que cuando iba todos los días a la oficina | CC17: Mayor que cuando iba todos los días a la oficina | CD17: Igual que cuando iba todos los días a la oficina | CE17: Igual que cuando iba todos los días a la oficina | CF17: Menores que cuando iba todos los días a la oficina | CG17: Igual que cuando iba todos los días a la oficina | CH17: Mayor que cuando iba todos los días a la oficina | CI17: Igual que cuando iba todos los días a la oficina | CJ17: Igual que cuando iba todos los días a la oficina | CK17: Mucho Mayor que cuando iba todos los días a la oficina | CL17: Igual que cuando iba todos los días a la oficina | CM17: Mejor que cuando iba todos los días a la oficina | CN17: Mucho Mayor que cuando iba todos los días a la oficina | CO17: Mayor que cuando iba todos los días a la oficina | CP17: Mayor que cuando iba todos los días a la oficina | CQ17: Mayor que cuando iba todos los días a la oficina | CR17: Mucho menor que cuando iba todos los días a la oficina | CS17: Mucho menores que cuando iba todos los días a la oficina | CT17: Igual que cuando iba todos los días a la oficina | CU17: Mayor que cuando iba todos los días a la oficina | CV17: andresbernalc@live.com.mx | CW17: 301+ empleados | CX17: =VLOOKUP(K17,Sheet2!$A$2:$B$58,2,0) -> 0 | CY17: =_xlfn.TEXTJOIN(",",FALSE,A17:CX17) -> 45564,0644939352,México,<35 años,Masculino,Universidad ,Como empleado de una empresa,Estados Unidos ,11-20 años,5-10 años,Analista de Transformación ,Gerente ,Conduent,>500 empleados.,Empresa que subcontrata (outsourcing) los servicios de otra empresa situada en otro país,Multinacional,Muy Frecuentemente,Alto,>5 días,Ninguno,Cuando es necesario y no existe otra opción ,Para renovar algún dato, recoger equipo o visita del cliente ,Cuando una persona en específico lo requiere ,Ninguna,Remota ( todos los días en casa),Consensuada por las dos partes,Totalmente en desacuerdo,Igual que cuando iba todos los días a la oficina,Mayor que cuando iba todos los días a la oficina,Igual que cuando iba todos los días a la oficina,Diferentes que cuando iba todos los días a la oficina, ahora necesito menos horas para hacer lo mismo,Todas por videoconferencia,Igual que cuando eran en la oficina,Mucho Mayor que cuando iba todos los días a la oficina,Mucho Mayor que cuando iba todos los días a la oficina,Mayor que cuando iba todos los días a la oficina,Mucho Mayor que cuando iba todos los días a la oficina,Mucho Mejor que cuando iba todos los días a la oficina,Mejora mi desempeño en el trabajo,Mejoran mi productividad,Mucho mayor que cuando iba todos los días a la oficina,Menor que cuando iba todos los días a la oficina,Igual que cuando iba todos los días a la oficina,Igual que cuando iba todos los días a la oficina,Igual que cuando iba todos los días a la oficina,Igual que cuando iba todos los días a la oficina,Igual que cuando iba todos los días a la oficina,Mucho menos que cuando iba todos los días a la oficina,Igual que cuando iba todos los días a la oficina,Mucho menos que cuando iba todos los días a la oficina,Igual que cuando iba todos los días a la oficina,Iguales que cuando iba todos los días a la oficina,Igual que cuando iba todos los días a la oficina,Igual que cuando iba todos los días a la oficina,Mayor que cuando iba todos los días a la oficina,Mucho Mayor que cuando iba todos los días a la oficina,Igual que cuando iba todos los días a la oficina,Igual que cuando iba todos los días a la oficina,Mayor que cuando iba todos los días a la oficina,Mayor que cuando iba todos los días a la oficina,Mucho menores que cuando iba todos los días a la oficina,Mayor que cuando iba todos los días a la oficina,Iguales que cuando iba todos los días a la oficina,Igual que cuando iba todos los días a la oficina,Iguales que cuando iba todos los días a la oficina,Iguales que cuando iba todos los días a la oficina,Igual que cuando iba todos los días a la oficina,Igual que cuando iba todos los días a la oficina,Menores que cuando iba todos los días a la oficina,Mayor que cuando iba todos los días a la oficina,Igual que cuando iba todos los días a la oficina,Igual que cuando iba todos los días a la oficina,Iguales que cuando iba todos los días a la oficina,Igual que cuando iba todos los días a la oficina,Igual que cuando iba todos los días a la oficina,Mucho Mayor que cuando iba todos los días a la oficina,Mucho mayor que cuando iba todos los días a la oficina,Mucho Mayor que cuando iba todos los días a la oficina,Mucho Mayor que cuando iba todos los días a la oficina,Mucho Mayor que cuando iba todos los días a la oficina,Mucho Mayor que cuando iba todos los días a la oficina,Mayor que cuando iba todos los días a la oficina,Igual que cuando iba todos los días a la oficina,Igual que cuando iba todos los días a la oficina,Menores que cuando iba todos los días a la oficina,Igual que cuando iba todos los días a la oficina,Mayor que cuando iba todos los días a la oficina,Igual que cuando iba todos los días a la oficina,Igual que cuando iba todos los días a la oficina,Mucho Mayor que cuando iba todos los días a la oficina,Igual que cuando iba todos los días a la oficina,Mejor que cuando iba todos los días a la oficina,Mucho Mayor que cuando iba todos los días a la oficina,Mayor que cuando iba todos los días a la oficina,Mayor que cuando iba todos los días a la oficina,Mayor que cuando iba todos los días a la oficina,Mucho menor que cuando iba todos los días a la oficina,Mucho menores que cuando iba todos los días a la oficina,Igual que cuando iba todos los días a la oficina,Mayor que cuando iba todos los días a la oficina,andresbernalc@live.com.mx,301+ empleados,0
A18: 45565.806 | B18: México | C18: <35 años | D18: Masculino | E18: Licenciatura | F18: De forma autónoma/independiente/freelance | H18: 5-10 años | I18: <5 años | J18: Front End Junior | K18: Creative Director | M18: <50 empleados | N18: Empresa que desarrolla software a medida partiendo desde cero | O18: Local | P18: Frecuentemente | Q18: Alto | R18: >5 días | S18: Ninguno | X18: Remota ( todos los días en casa) | Y18: Decidida por ti | Z18: En desacuerdo | AA18: Mayor que cuando iba todos los días a la oficina | AB18: Mayor que cuando iba todos los días a la oficina | AC18: Mayor que cuando iba todos los días a la oficina | AD18: Diferentes que cuando iba todos los días a la oficina, ahora necesito menos horas para hacer lo mismo | AE18: Todas por videoconferencia | AF18: Mucho menor que cuando eran en la oficina | AG18: Mucho Mayor que cuando iba todos los días a la oficina | AH18: Mucho Mayor que cuando iba todos los días a la oficina | AI18: Mucho Mayor que cuando iba todos los días a la oficina | AJ18: Mucho Mayor que cuando iba todos los días a la oficina | AK18: Mayor que cuando iba todos los días a la oficina | AL18: Mejora mucho mi desempeño en el trabajo | AM18: Mejoran mi productividad | AN18: Mayor que cuando iba todos los días a la oficina | AO18: Mucho mayor que cuando iba todos los días a la oficina | AP18: Mucho menos que cuando iba todos los días a la oficina | AQ18: Igual que cuando iba todos los días a la oficina | AR18: Menos que cuando iba todos los días a la oficina | AS18: Menos que cuando iba todos los días a la oficina | AT18: Igual que cuando iba todos los días a la oficina | AU18: Menos que cuando iba todos los días a la oficina | AV18: Mucho menos que cuando iba todos los días a la oficina | AW18: Mucho menos que cuando iba todos los días a la oficina | AX18: Igual que cuando iba todos los días a la oficina | AY18: Iguales que cuando iba todos los días a la oficina | AZ18: Menor que cuando iba todos los días a la oficina | BA18: Igual que cuando iba todos los días a la oficina | BB18: Mucho menor que cuando iba todos los días a la oficina | BC18: Mucho Mayor que cuando iba todos los días a la oficina | BD18: Menor que cuando iba todos los días a la oficina | BE18: Mucho menor que cuando iba todos los días a la oficina | BF18: Menor que cuando iba todos los días a la oficina | BG18: Mucho mayor que cuando iba todos los días a la oficina | BH18: Menores que cuando iba todos los días a la oficina | BI18: Igual que cuando iba todos los días a la oficina | BJ18: Menores que cuando iba todos los días a la oficina | BK18: Igual que cuando iba todos los días a la oficina | BL18: Menores que cuando iba todos los días a la oficina | BM18: Iguales que cuando iba todos los días a la oficina | BN18: Mucho menos que cuando iba todos los días a la oficina | BO18: Igual que cuando iba todos los días a la oficina | BP18: Mucho menores que cuando iba todos los días a la oficina | BQ18: Mayor que cuando iba todos los días a la oficina | BR18: Igual que cuando iba todos los días a la oficina | BS18: Mucho menos que cuando iba todos los días a la oficina | BT18: Menores que cuando iba todos los días a la oficina | BU18: Mejor que cuando iba todos los días a la oficina | BV18: Mayor que cuando iba todos los días a la oficina | BW18: Mayor que cuando iba todos los días a la oficina | BX18: Mucho mayor que cuando iba todos los días a la oficina | BY18: Mayor que cuando iba todos los días a la oficina | BZ18: Mucho Mayor que cuando iba todos los días a la oficina | CA18: Mayor que cuando iba todos los días a la oficina | CB18: Mayor que cuando iba todos los días a la oficina | CC18: Mayor que cuando iba todos los días a la oficina | CD18: Menor que cuando iba todos los días a la oficina | CE18: Mas que cuando iba todos los días a la oficina | CF18: Iguales que cuando iba todos los días a la oficina | CG18: Mayor que cuando iba todos los días a la oficina | CH18: Mucho Mayor que cuando iba todos los días a la oficina | CI18: Mucho Mayor que cuando iba todos los días a la oficina | CJ18: Mucho menor que cuando iba todos los días a la oficina | CK18: Mayor que cuando iba todos los días a la oficina | CL18: Menor que cuando iba todos los días a la oficina | CM18: Mejor que cuando iba todos los días a la oficina | CN18: Mayor que cuando iba todos los días a la oficina | CO18: Menor que cuando iba todos los días a la oficina | CP18: Mayor que cuando iba todos los días a la oficina | CQ18: Mayor que cuando iba todos los días a la oficina | CR18: Menor que cuando iba todos los días a la oficina | CS18: Menores que cuando iba todos los días a la oficina | CT18: Igual que cuando iba todos los días a la oficina | CU18: Mayor que cuando iba todos los días a la oficina | CV18: clubdecinecc@gmail.com | CW18: <301 empleados | CX18: =VLOOKUP(K18,Sheet2!$A$2:$B$58,2,0) -> 0 | CY18: =_xlfn.TEXTJOIN(",",FALSE,A18:CX18) -> 45565,8057715972,México,<35 años,Masculino,Licenciatura,De forma autónoma/independiente/freelance,,5-10 años,<5 años,Front End Junior,Creative Director,,<50 empleados,Empresa que desarrolla software a medida partiendo desde cero,Local,Frecuentemente,Alto,>5 días,Ninguno,,,,,Remota ( todos los días en casa),Decidida por ti,En desacuerdo,Mayor que cuando iba todos los días a la oficina,Mayor que cuando iba todos los días a la oficina,Mayor que cuando iba todos los días a la oficina,Diferentes que cuando iba todos los días a la oficina, ahora necesito menos horas para hacer lo mismo,Todas por videoconferencia,Mucho menor que cuando eran en la oficina,Mucho Mayor que cuando iba todos los días a la oficina,Mucho Mayor que cuando iba todos los días a la oficina,Mucho Mayor que cuando iba todos los días a la oficina,Mucho Mayor que cuando iba todos los días a la oficina,Mayor que cuando iba todos los días a la oficina,Mejora mucho mi desempeño en el trabajo,Mejoran mi productividad,Mayor que cuando iba todos los días a la oficina,Mucho mayor que cuando iba todos los días a la oficina,Mucho menos que cuando iba todos los días a la oficina,Igual que cuando iba todos los días a la oficina,Menos que cuando iba todos los días a la oficina,Menos que cuando iba todos los días a la oficina,Igual que cuando iba todos los días a la oficina,Menos que cuando iba todos los días a la oficina,Mucho menos que cuando iba todos los días a la oficina,Mucho menos que cuando iba todos los días a la oficina,Igual que cuando iba todos los días a la oficina,Iguales que cuando iba todos los días a la oficina,Menor que cuando iba todos los días a la oficina,Igual que cuando iba todos los días a la oficina,Mucho menor que cuando iba todos los días a la oficina,Mucho Mayor que cuando iba todos los días a la oficina,Menor que cuando iba todos los días a la oficina,Mucho menor que cuando iba todos los días a la oficina,Menor que cuando iba todos los días a la oficina,Mucho mayor que cuando iba todos los días a la oficina,Menores que cuando iba todos los días a la oficina,Igual que cuando iba todos los días a la oficina,Menores que cuando iba todos los días a la oficina,Igual que cuando iba todos los días a la oficina,Menores que cuando iba todos los días a la oficina,Iguales que cuando iba todos los días a la oficina,Mucho menos que cuando iba todos los días a la oficina,Igual que cuando iba todos los días a la oficina,Mucho menores que cuando iba todos los días a la oficina,Mayor que cuando iba todos los días a la oficina,Igual que cuando iba todos los días a la oficina,Mucho menos que cuando iba todos los días a la oficina,Menores que cuando iba todos los días a la oficina,Mejor que cuando iba todos los días a la oficina,Mayor que cuando iba todos los días a la oficina,Mayor que cuando iba todos los días a la oficina,Mucho mayor que cuando iba todos los días a la oficina,Mayor que cuando iba todos los días a la oficina,Mucho Mayor que cuando iba todos los días a la oficina,Mayor que cuando iba todos los días a la oficina,Mayor que cuando iba todos los días a la oficina,Mayor que cuando iba todos los días a la oficina,Menor que cuando iba todos los días a la oficina,Mas que cuando iba todos los días a la oficina,Iguales que cuando iba todos los días a la oficina,Mayor que cuando iba todos los días a la oficina,Mucho Mayor que cuando iba todos los días a la oficina,Mucho Mayor que cuando iba todos los días a la oficina,Mucho menor que cuando iba todos los días a la oficina,Mayor que cuando iba todos los días a la oficina,Menor que cuando iba todos los días a la oficina,Mejor que cuando iba todos los días a la oficina,Mayor que cuando iba todos los días a la oficina,Menor que cuando iba todos los días a la oficina,Mayor que cuando iba todos los días a la oficina,Mayor que cuando iba todos los días a la oficina,Menor que cuando iba todos los días a la oficina,Menores que cuando iba todos los días a la oficina,Igual que cuando iba todos los días a la oficina,Mayor que cuando iba todos los días a la oficina,clubdecinecc@gmail.com,<301 empleados,0
A19: 45562.101 | B19: México | C19: <35 años | D19: Femenino | E19: Licenciatura | F19: De ambas formas | G19: United Kingdom | H19: <5 años | I19: <5 años | J19: Marketing Director | K19: Marketing Expert - Account Manager | L19: UENI | M19: 51-150 empleados | N19: Empresa que desarrolla software a medida partiendo desde cero | O19: Multinacional | P19: Muy Frecuentemente | Q19: Alto | R19: >5 días | S19: Ninguno | T19: Nunca | U19: Nunca | V19: Nunca | W19: No | X19: Remota ( todos los días en casa) | Y19: Consensuada por las dos partes | Z19: En desacuerdo | AA19: Mucho menor que cuando iba todos los días a la oficina | AB19: Mucho menor que cuando iba todos los días a la oficina | AC19: Mucho menor que cuando iba todos los días a la oficina | AD19: Muy diferentes que cuando iba todos los días a la oficina, ahora necesito muchas menos horas para hacer lo mismo | AE19: Todas por videoconferencia | AF19: Menor que cuando eran en la oficina | AG19: Mucho Mayor que cuando iba todos los días a la oficina | AH19: Mayor que cuando iba todos los días a la oficina | AI19: Mayor que cuando iba todos los días a la oficina | AJ19: Mayor que cuando iba todos los días a la oficina | AK19: Igual que cuando iba todos los días a la oficina | AL19: Mejora mi desempeño en el trabajo | AM19: Mejoran mi productividad | AN19: Menor que cuando iba todos los días a la oficina | AO19: Menor que cuando iba todos los días a la oficina | AP19: Más que cuando iba todos los días a la oficina | AQ19: Mucho menos que cuando iba todos los días a la oficina | AR19: Más que cuando iba todos los días a la oficina | AS19: Más que cuando iba todos los días a la oficina | AT19: Mucho más que cuando iba todos los días a la oficina | AU19: Mas que cuando iba todos los días a la oficina | AV19: Menos que cuando iba todos los días a la oficina | AW19: Menos que cuando iba todos los días a la oficina | AX19: Igual que cuando iba todos los días a la oficina | AY19: Mayores que cuando iba todos los días a la oficina | AZ19: Mayor que cuando iba todos los días a la oficina | BA19: Mayor que cuando iba todos los días a la oficina | BB19: Mucho menor que cuando iba todos los días a la oficina | BC19: Igual que cuando iba todos los días a la oficina | BD19: Mucho menor que cuando iba todos los días a la oficina | BE19: Mucho menor que cuando iba todos los días a la oficina | BF19: Mucho menor que cuando iba todos los días a la oficina | BG19: Mayor que cuando iba todos los días a la oficina | BH19: Iguales que cuando iba todos los días a la oficina | BI19: Mayor que cuando iba todos los días a la oficina | BJ19: Iguales que cuando iba todos los días a la oficina | BK19: Mayor que cuando iba todos los días a la oficina | BL19: Mucho menores que cuando iba todos los días a la oficina | BM19: Iguales que cuando iba todos los días a la oficina | BN19: Igual que cuando iba todos los días a la oficina | BO19: Igual que cuando iba todos los días a la oficina | BP19: Mucho menores que cuando iba todos los días a la oficina | BQ19: Mucho mayor que cuando iba todos los días a la oficina | BR19: Mayor que cuando iba todos los días a la oficina | BS19: Mucho menos que cuando iba todos los días a la oficina | BT19: Mucho menores que cuando iba todos los días a la oficina | BU19: Mejor que cuando iba todos los días a la oficina | BV19: Mayor que cuando iba todos los días a la oficina | BW19: Mayor que cuando iba todos los días a la oficina | BX19: Mayor que cuando iba todos los días a la oficina | BY19: Mayor que cuando iba todos los días a la oficina | BZ19: Mayor que cuando iba todos los días a la oficina | CA19: Mayor que cuando iba todos los días a la oficina | CB19: Mucho Mayor que cuando iba todos los días a la oficina | CC19: Mayor que cuando iba todos los días a la oficina | CD19: Igual que cuando iba todos los días a la oficina | CE19: Igual que cuando iba todos los días a la oficina | CF19: Mayores que cuando iba todos los días a la oficina | CG19: Mayor que cuando iba todos los días a la oficina | CH19: Mayor que cuando iba todos los días a la oficina | CI19: Mayor que cuando iba todos los días a la oficina | CJ19: Menor que cuando iba todos los días a la oficina | CK19: Menor que cuando iba todos los días a la oficina | CL19: Mucho menor que cuando iba todos los días a la oficina | CM19: Mejor que cuando iba todos los días a la oficina | CN19: Mayor que cuando iba todos los días a la oficina | CO19: Igual que cuando iba todos los días a la oficina | CP19: Igual que cuando iba todos los días a la oficina | CQ19: Mayor que cuando iba todos los días a la oficina | CR19: Mucho menor que cuando iba todos los días a la oficina | CS19: Iguales que cuando iba todos los días a la oficina | CT19: Mayor que cuando iba todos los días a la oficina | CU19: Mayor que cuando iba todos los días a la oficina | CV19: vmadrigalguevara@gmail.com | CW19: <301 empleados | CX19: =VLOOKUP(K19,Sheet2!$A$2:$B$58,2,0) -> 0 | CY19: =_xlfn.TEXTJOIN(",",FALSE,A19:CX19) -> 45562,1007490509,México,<35 años,Femenino,Licenciatura ,De ambas formas,United Kingdom,<5 años,<5 años,Marketing Director ,Marketing Expert - Account Manager ,UENI ,51-150 empleados,Empresa que desarrolla software a medida partiendo desde cero,Multinacional,Muy Frecuentemente,Alto,>5 días,Ninguno,Nunca ,Nunca ,Nunca ,No,Remota ( todos los días en casa),Consensuada por las dos partes,En desacuerdo,Mucho menor que cuando iba todos los días a la oficina,Mucho menor que cuando iba todos los días a la oficina,Mucho menor que cuando iba todos los días a la oficina,Muy diferentes que cuando iba todos los días a la oficina, ahora necesito muchas menos horas para hacer lo mismo,Todas por videoconferencia,Menor que cuando eran en la oficina,Mucho Mayor que cuando iba todos los días a la oficina,Mayor que cuando iba todos los días a la oficina,Mayor que cuando iba todos los días a la oficina,Mayor que cuando iba todos los días a la oficina,Igual que cuando iba todos los días a la oficina,Mejora mi desempeño en el trabajo,Mejoran mi productividad,Menor que cuando iba todos los días a la oficina,Menor que cuando iba todos los días a la oficina,Más que cuando iba todos los días a la oficina,Mucho menos que cuando iba todos los días a la oficina,Más que cuando iba todos los días a la oficina,Más que cuando iba todos los días a la oficina,Mucho más que cuando iba todos los días a la oficina,Mas que cuando iba todos los días a la oficina,Menos que cuando iba todos los días a la oficina,Menos que cuando iba todos los días a la oficina,Igual que cuando iba todos los días a la oficina,Mayores que cuando iba todos los días a la oficina,Mayor que cuando iba todos los días a la oficina,Mayor que cuando iba todos los días a la oficina,Mucho menor que cuando iba todos los días a la oficina,Igual que cuando iba todos los días a la oficina,Mucho menor que cuando iba todos los días a la oficina,Mucho menor que cuando iba todos los días a la oficina,Mucho menor que cuando iba todos los días a la oficina,Mayor que cuando iba todos los días a la oficina,Iguales que cuando iba todos los días a la oficina,Mayor que cuando iba todos los días a la oficina,Iguales que cuando iba todos los días a la oficina,Mayor que cuando iba todos los días a la oficina,Mucho menores que cuando iba todos los días a la oficina,Iguales que cuando iba todos los días a la oficina,Igual que cuando iba todos los días a la oficina,Igual que cuando iba todos los días a la oficina,Mucho menores que cuando iba todos los días a la oficina,Mucho mayor que cuando iba todos los días a la oficina,Mayor que cuando iba todos los días a la oficina,Mucho menos que cuando iba todos los días a la oficina,Mucho menores que cuando iba todos los días a la oficina,Mejor que cuando iba todos los días a la oficina,Mayor que cuando iba todos los días a la oficina,Mayor que cuando iba todos los días a la oficina,Mayor que cuando iba todos los días a la oficina,Mayor que cuando iba todos los días a la oficina,Mayor que cuando iba todos los días a la oficina,Mayor que cuando iba todos los días a la oficina,Mucho Mayor que cuando iba todos los días a la oficina,Mayor que cuando iba todos los días a la oficina,Igual que cuando iba todos los días a la oficina,Igual que cuando iba todos los días a la oficina,Mayores que cuando iba todos los días a la oficina,Mayor que cuando iba todos los días a la oficina,Mayor que cuando iba todos los días a la oficina,Mayor que cuando iba todos los días a la oficina,Menor que cuando iba todos los días a la oficina,Menor que cuando iba todos los días a la oficina,Mucho menor que cuando iba todos los días a la oficina,Mejor que cuando iba todos los días a la oficina,Mayor que cuando iba todos los días a la oficina,Igual que cuando iba todos los días a la oficina,Igual que cuando iba todos los días a la oficina,Mayor que cuando iba todos los días a la oficina,Mucho menor que cuando iba todos los días a la oficina,Iguales que cuando iba todos los días a la oficina,Mayor que cuando iba todos los días a la oficina,Mayor que cuando iba todos los días a la oficina,vmadrigalguevara@gmail.com,<301 empleados,0
A20: 45561.792 | B20: Colombia | C20: <35 años | D20: Masculino | E20: Maestria | F20: Como empleado de una empresa | G20: Colombia | H20: 21-30 años | I20: 10-20 años | J20: Director de ingeniería | K20: Director de ingeniería | L20: Asesoftware | M20: >500 empleados. | N20: Empresa que desarrolla software a medida partiendo desde cero | O20: Nacional (múltiples sedes en el mismo país) | P20: A veces | Q20: Bajo | R20: 1-2 días | S20: 3-4 días | V20: Visitas con clientes; Sesiones de gerencia mensual | W20: No | X20: Híbrida oficina (más días en la oficina que en casa) | Y20: Decidida por ti | Z20: De acuerdo | AA20: Menor que cuando iba todos los días a la oficina | AB20: Menor que cuando iba todos los días a la oficina | AC20: Igual que cuando iba todos los días a la oficina | AD20: Iguales que cuando iba todos los días a la oficina | AE20: Casi todas por videoconferencia | AF20: Mayor que cuando eran en la oficina | AG20: Menor cuando iba todos los días a la oficina | AH20: Menor que cuando iba todos los días a la oficina | AI20: Menor que cuando iba todos los días a la oficina | AJ20: Mayor que cuando iba todos los días a la oficina | AK20: Igual que cuando iba todos los días a la oficina | AL20: No me influye | AM20: No afectan a mi productividad | AN20: Menor que cuando iba todos los días a la oficina | AO20: Mayor que cuando iba todos los días a la oficina | AP20: Más que cuando iba todos los días a la oficina | AQ20: No trabajo con personas de distintas culturas | AR20: Igual que cuando iba todos los días a la oficina | AS20: Igual que cuando iba todos los días a la oficina | AT20: Más que cuando iba todos los días a la oficina | AU20: Mas que cuando iba todos los días a la oficina | AV20: Mas que cuando iba todos los días a la oficina | AW20: Mas que cuando iba todos los días a la oficina | AX20: Mas que cuando iba todos los días a la oficina | AY20: Iguales que cuando iba todos los días a la oficina | AZ20: Menor que cuando iba todos los días a la oficina | BA20: Igual que cuando iba todos los días a la oficina | BB20: Mayor que cuando iba todos los días a la oficina | BC20: Igual que cuando iba todos los días a la oficina | BD20: Igual que cuando iba todos los días a la oficina | BE20: Mayor que cuando iba todos los días a la oficina | BF20: Igual que cuando iba todos los días a la oficina | BG20: Mayor que cuando iba todos los días a la oficina | BH20: Iguales que cuando iba todos los días a la oficina | BI20: Igual que cuando iba todos los días a la oficina | BJ20: No hay diferencias culturales en mi equipo | BK20: Menor que cuando iba todos los días a la oficina | BL20: Mayores que cuando iba todos los días a la oficina | BM20: No tengo que utilizar diferentes idiomas en mi trabajo | BN20: Igual que cuando iba todos los días a la oficina | BO20: Menor que cuando iba todos los días a la oficina | BP20: Iguales que cuando iba todos los días a la oficina | BQ20: Igual que cuando iba todos los días a la oficina | BR20: Mayor que cuando iba todos los días a la oficina | BS20: Más que cuando iba todos los días a la oficina | BT20: Mayores que cuando iba todos los días a la oficina | BU20: Peor que cuando iba todos los días a la oficina | BV20: Igual que cuando iba todos los días a la oficina | BW20: Igual que cuando iba todos los días a la oficina | BX20: Mayor que cuando iba todos los días a la oficina | BY20: Igual que cuando iba todos los días a la oficina | BZ20: Igual que cuando iba todos los días a la oficina | CA20: Menor que cuando iba todos los días a la oficina | CB20: Igual que cuando iba todos los días a la oficina | CC20: Igual que cuando iba todos los días a la oficina | CD20: Mayor que cuando iba todos los días a la oficina | CE20: Igual que cuando iba todos los días a la oficina | CF20: Menores que cuando iba todos los días a la oficina | CG20: Menor que cuando iba todos los días a la oficina | CH20: Igual que cuando iba todos los días a la oficina | CI20: Menor que cuando iba todos los días a la oficina | CJ20: Igual que cuando iba todos los días a la oficina | CK20: Mucho menor que cuando iba todos los días a la oficina | CL20: Igual que cuando iba todos los días a la oficina | CM20: Igual que cuando iba todos los días a la oficina | CN20: Menor que cuando iba todos los días a la oficina | CO20: Menor que cuando iba todos los días a la oficina | CP20: Menor que cuando iba todos los días a la oficina | CQ20: Mayor que cuando iba todos los días a la oficina | CR20: Menor que cuando iba todos los días a la oficina | CS20: Mayores que cuando iba todos los días a la oficina | CT20: Menor que cuando iba todos los días a la oficina | CU20: Menor que cuando iba todos los días a la oficina | CV20: crodriguez@asesoftware.com | CW20: 301+ empleados | CX20: =VLOOKUP(K20,Sheet2!$A$2:$B$58,2,0) -> 0 | CY20: =_xlfn.TEXTJOIN(",",FALSE,A20:CX20) -> 45561,7923798032,Colombia,<35 años,Masculino,Maestria,Como empleado de una empresa,Colombia,21-30 años,10-20 años,Director de ingeniería,Director de ingeniería,Asesoftware,>500 empleados.,Empresa que desarrolla software a medida partiendo desde cero,Nacional (múltiples sedes en el mismo país),A veces,Bajo,1-2 días,3-4 días,,,Visitas con clientes; Sesiones de gerencia mensual,No,Híbrida oficina (más días en la oficina que en casa),Decidida por ti,De acuerdo,Menor que cuando iba todos los días a la oficina,Menor que cuando iba todos los días a la oficina,Igual que cuando iba todos los días a la oficina,Iguales que cuando iba todos los días a la oficina,Casi todas por videoconferencia,Mayor que cuando eran en la oficina,Menor cuando iba todos los días a la oficina,Menor que cuando iba todos los días a la oficina,Menor que cuando iba todos los días a la oficina,Mayor que cuando iba todos los días a la oficina,Igual que cuando iba todos los días a la oficina,No me influye,No afectan a mi productividad,Menor que cuando iba todos los días a la oficina,Mayor que cuando iba todos los días a la oficina,Más que cuando iba todos los días a la oficina,No trabajo con personas de distintas culturas,Igual que cuando iba todos los días a la oficina,Igual que cuando iba todos los días a la oficina,Más que cuando iba todos los días a la oficina,Mas que cuando iba todos los días a la oficina,Mas que cuando iba todos los días a la oficina,Mas que cuando iba todos los días a la oficina,Mas que cuando iba todos los días a la oficina,Iguales que cuando iba todos los días a la oficina,Menor que cuando iba todos los días a la oficina,Igual que cuando iba todos los días a la oficina,Mayor que cuando iba todos los días a la oficina,Igual que cuando iba todos los días a la oficina,Igual que cuando iba todos los días a la oficina,Mayor que cuando iba todos los días a la oficina,Igual que cuando iba todos los días a la oficina,Mayor que cuando iba todos los días a la oficina,Iguales que cuando iba todos los días a la oficina,Igual que cuando iba todos los días a la oficina,No hay diferencias culturales en mi equipo,Menor que cuando iba todos los días a la oficina,Mayores que cuando iba todos los días a la oficina,No tengo que utilizar diferentes idiomas en mi trabajo,Igual que cuando iba todos los días a la oficina,Menor que cuando iba todos los días a la oficina,Iguales que cuando iba todos los días a la oficina,Igual que cuando iba todos los días a la oficina,Mayor que cuando iba todos los días a la oficina,Más que cuando iba todos los días a la oficina,Mayores que cuando iba todos los días a la oficina,Peor que cuando iba todos los días a la oficina,Igual que cuando iba todos los días a la oficina,Igual que cuando iba todos los días a la oficina,Mayor que cuando iba todos los días a la oficina,Igual que cuando iba todos los días a la oficina,Igual que cuando iba todos los días a la oficina,Menor que cuando iba todos los días a la oficina,Igual que cuando iba todos los días a la oficina,Igual que cuando iba todos los días a la oficina,Mayor que cuando iba todos los días a la oficina,Igual que cuando iba todos los días a la oficina,Menores que cuando iba todos los días a la oficina,Menor que cuando iba todos los días a la oficina,Igual que cuando iba todos los días a la oficina,Menor que cuando iba todos los días a la oficina,Igual que cuando iba todos los días a la oficina,Mucho menor que cuando iba todos los días a la oficina,Igual que cuando iba todos los días a la oficina,Igual que cuando iba todos los días a la oficina,Menor que cuando iba todos los días a la oficina,Menor que cuando iba todos los días a la oficina,Menor que cuando iba todos los días a la oficina,Mayor que cuando iba todos los días a la oficina,Menor que cuando iba todos los días a la oficina,Mayores que cuando iba todos los días a la oficina,Menor que cuando iba todos los días a la oficina,Menor que cuando iba todos los días a la oficina,crodriguez@asesoftware.com,301+ empleados,0
A21: 45562.698 | B21: Colombia | C21: <35 años | D21: Masculino | E21: Maestría | F21: Como empleado de una empresa | G21: Colombia | H21: 11-20 años | I21: 10-20 años | J21: Gerente de Arquitectura | K21: Gerente de Arquitectura | M21: >500 empleados. | N21: Empresa que subcontrata (outsourcing) los servicios de otra del mismo país | O21: Local | P21: Nunca | Q21: Bajo | R21: 1-2 días | S21: 3-4 días | X21: Híbrida casa (más días en casa que en la oficina) | Y21: Impuesta por la empresa | Z21: De acuerdo | AA21: Menor que cuando iba todos los días a la oficina | AB21: Menor que cuando iba todos los días a la oficina | AC21: Menor que cuando iba todos los días a la oficina | AD21: Iguales que cuando iba todos los días a la oficina | AE21: La Mitad por videoconferencia y la mitad presencial | AF21: Igual que cuando eran en la oficina | AG21: Mayor que cuando iba todos los días a la oficina | AH21: Menor que cuando iba todos los días a la oficina | AI21: Menor que cuando iba todos los días a la oficina | AJ21: Mayor que cuando iba todos los días a la oficina | AK21: Igual que cuando iba todos los días a la oficina | AL21: No me influye | AM21: Mejoran mucho mi productividad | AN21: Menor que cuando iba todos los días a la oficina | AO21: Igual que cuando iba todos los días a la oficina | AP21: Mucho más que cuando iba todos los días a la oficina | AQ21: No trabajo con personas de distintas culturas | AR21: No trabajo con personas con un horario distinto al mío | AS21: Mucho menos que cuando iba todos los días a la oficina | AT21: Más que cuando iba todos los días a la oficina | AU21: Mas que cuando iba todos los días a la oficina | AV21: Mas que cuando iba todos los días a la oficina | AW21: Mas que cuando iba todos los días a la oficina | AX21: Mucho mas que cuando iba todos los días a la oficina | AY21: Iguales que cuando iba todos los días a la oficina | AZ21: Igual que cuando iba todos los días a la oficina | BA21: Menor que cuando iba todos los días a la oficina | BB21: Mucho menor que cuando iba todos los días a la oficina | BC21: Igual que cuando iba todos los días a la oficina | BD21: Igual que cuando iba todos los días a la oficina | BE21: Igual que cuando iba todos los días a la oficina | BF21: Igual que cuando iba todos los días a la oficina | BG21: Mayor que cuando iba todos los días a la oficina | BH21: Mucho menores que cuando iba todos los días a la oficina | BI21: Igual que cuando iba todos los días a la oficina | BJ21: No hay diferencias culturales en mi equipo | BK21: Mayor que cuando iba todos los días a la oficina | BL21: Mayores que cuando iba todos los días a la oficina | BM21: No tengo que utilizar diferentes idiomas en mi trabajo | BN21: No trabajo con personas con distintos horarios | BO21: Menor que cuando iba todos los días a la oficina | BP21: Mucho menores que cuando iba todos los días a la oficina | BQ21: Mayor que cuando iba todos los días a la oficina | BR21: Mayor que cuando iba todos los días a la oficina | BS21: Más que cuando iba todos los días a la oficina | BT21: Mayores que cuando iba todos los días a la oficina | BU21: Igual que cuando iba todos los días a la oficina | BV21: Menor que cuando iba todos los días a la oficina | BW21: Mayor que cuando iba todos los días a la oficina | BX21: Mucho mayor que cuando iba todos los días a la oficina | BY21: Menor que cuando iba todos los días a la oficina | BZ21: Menor que cuando iba todos los días a la oficina | CA21: Igual que cuando iba todos los días a la oficina | CB21: Mayor que cuando iba todos los días a la oficina | CC21: Igual que cuando iba todos los días a la oficina | CD21: Mucho mayor que cuando iba todos los días a la oficina | CE21: Igual que cuando iba todos los días a la oficina | CF21: Iguales que cuando iba todos los días a la oficina | CG21: Menor que cuando iba todos los días a la oficina | CH21: Mucho Mayor que cuando iba todos los días a la oficina | CI21: Menor que cuando iba todos los días a la oficina | CJ21: Igual que cuando iba todos los días a la oficina | CK21: Menor que cuando iba todos los días a la oficina | CL21: Igual que cuando iba todos los días a la oficina | CM21: Peor que cuando iba todos los días a la oficina | CN21: Menor que cuando iba todos los días a la oficina | CO21: Mucho menor que cuando iba todos los días a la oficina | CP21: Menor que cuando iba todos los días a la oficina | CQ21: Mayor que cuando iba todos los días a la oficina | CR21: Mayor que cuando iba todos los días a la oficina | CS21: Mayores que cuando iba todos los días a la oficina | CT21: Igual que cuando iba todos los días a la oficina | CU21: Igual que cuando iba todos los días a la oficina | CV21: danserrano@gmail.com | CW21: 301+ empleados | CX21: =VLOOKUP(K21,Sheet2!$A$2:$B$58,2,0) -> 0 | CY21: =_xlfn.TEXTJOIN(",",FALSE,A21:CX21) -> 45562,6980172801,Colombia,<35 años,Masculino,Maestría,Como empleado de una empresa,Colombia,11-20 años,10-20 años,Gerente de Arquitectura,Gerente de Arquitectura,,>500 empleados.,Empresa que subcontrata (outsourcing) los servicios de otra del mismo país,Local,Nunca,Bajo,1-2 días,3-4 días,,,,,Híbrida casa (más días en casa que en la oficina),Impuesta por la empresa,De acuerdo,Menor que cuando iba todos los días a la oficina,Menor que cuando iba todos los días a la oficina,Menor que cuando iba todos los días a la oficina,Iguales que cuando iba todos los días a la oficina,La Mitad por videoconferencia y la mitad presencial,Igual que cuando eran en la oficina,Mayor que cuando iba todos los días a la oficina,Menor que cuando iba todos los días a la oficina,Menor que cuando iba todos los días a la oficina,Mayor que cuando iba todos los días a la oficina,Igual que cuando iba todos los días a la oficina,No me influye,Mejoran mucho mi productividad,Menor que cuando iba todos los días a la oficina,Igual que cuando iba todos los días a la oficina,Mucho más que cuando iba todos los días a la oficina,No trabajo con personas de distintas culturas,No trabajo con personas con un horario distinto al mío,Mucho menos que cuando iba todos los días a la oficina,Más que cuando iba todos los días a la oficina,Mas que cuando iba todos los días a la oficina,Mas que cuando iba todos los días a la oficina,Mas que cuando iba todos los días a la oficina,Mucho mas que cuando iba todos los días a la oficina,Iguales que cuando iba todos los días a la oficina,Igual que cuando iba todos los días a la oficina,Menor que cuando iba todos los días a la oficina,Mucho menor que cuando iba todos los días a la oficina,Igual que cuando iba todos los días a la oficina,Igual que cuando iba todos los días a la oficina,Igual que cuando iba todos los días a la oficina,Igual que cuando iba todos los días a la oficina,Mayor que cuando iba todos los días a la oficina,Mucho menores que cuando iba todos los días a la oficina,Igual que cuando iba todos los días a la oficina,No hay diferencias culturales en mi equipo,Mayor que cuando iba todos los días a la oficina,Mayores que cuando iba todos los días a la oficina,No tengo que utilizar diferentes idiomas en mi trabajo,No trabajo con personas con distintos horarios,Menor que cuando iba todos los días a la oficina,Mucho menores que cuando iba todos los días a la oficina,Mayor que cuando iba todos los días a la oficina,Mayor que cuando iba todos los días a la oficina,Más que cuando iba todos los días a la oficina,Mayores que cuando iba todos los días a la oficina,Igual que cuando iba todos los días a la oficina,Menor que cuando iba todos los días a la oficina,Mayor que cuando iba todos los días a la oficina,Mucho mayor que cuando iba todos los días a la oficina,Menor que cuando iba todos los días a la oficina,Menor que cuando iba todos los días a la oficina,Igual que cuando iba todos los días a la oficina,Mayor que cuando iba todos los días a la oficina,Igual que cuando iba todos los días a la oficina,Mucho mayor que cuando iba todos los días a la oficina,Igual que cuando iba todos los días a la oficina,Iguales que cuando iba todos los días a la oficina,Menor que cuando iba todos los días a la oficina,Mucho Mayor que cuando iba todos los días a la oficina,Menor que cuando iba todos los días a la oficina,Igual que cuando iba todos los días a la oficina,Menor que cuando iba todos los días a la oficina,Igual que cuando iba todos los días a la oficina,Peor que cuando iba todos los días a la oficina,Menor que cuando iba todos los días a la oficina,Mucho menor que cuando iba todos los días a la oficina,Menor que cuando iba todos los días a la oficina,Mayor que cuando iba todos los días a la oficina,Mayor que cuando iba todos los días a la oficina,Mayores que cuando iba todos los días a la oficina,Igual que cuando iba todos los días a la oficina,Igual que cuando iba todos los días a la oficina,danserrano@gmail.com,301+ empleados,0
